{
"highlevel": {
    "danceability": {
        "all": {
            "danceable": 0.998881220818,
            "not_danceable": 0.00111877184827
        },
        "probability": 0.998881220818,
        "value": "danceable"
    },
    "gender": {
        "all": {
            "female": 0.93848502636,
            "male": 0.0615149959922
        },
        "probability": 0.93848502636,
        "value": "female"
    },
    "genre_electronic": {
        "all": {
            "ambient": 0.0726199522614,
            "dnb": 0.358860701323,
            "house": 0.470333904028,
            "techno": 0.0235658735037,
            "trance": 0.0746195614338
        },
        "probability": 0.470333904028,
        "value": "house"
    },
    "mood_acoustic": {
        "all": {
            "acoustic": 0.00292868283577,
            "not_acoustic": 0.997071325779
        },
        "probability": 0.997071325779,
        "value": "not_acoustic"
    },
    "mood_aggressive": {
        "all": {
            "aggressive": 0.0614144615829,
            "not_aggressive": 0.938585519791
        },
        "probability": 0.938585519791,
        "value": "not_aggressive"
    },
    "mood_electronic": {
        "all": {
            "electronic": 0.729044854641,
            "not_electronic": 0.270955145359
        },
        "probability": 0.729044854641,
        "value": "electronic"
    },
    "mood_happy": {
        "all": {
            "happy": 0.72600787878,
            "not_happy": 0.273992151022
        },
        "probability": 0.72600787878,
        "value": "happy"
    },
    "mood_party": {
        "all": {
            "not_party": 0.239026069641,
            "party": 0.760973930359
        },
        "probability": 0.760973930359,
        "value": "party"
    },
    "mood_relaxed": {
        "all": {
            "not_relaxed": 0.760891020298,
            "relaxed": 0.239108964801
        },
        "probability": 0.760891020298,
        "value": "not_relaxed"
    },
    "mood_sad": {
        "all": {
            "not_sad": 0.918684482574,
            "sad": 0.0813155025244
        },
        "probability": 0.918684482574,
        "value": "not_sad"
    },
    "moods_mirex": {
        "all": {
            "Cluster1": 0.178693234921,
            "Cluster2": 0.200389578938,
            "Cluster3": 0.0844113603234,
            "Cluster4": 0.346445262432,
            "Cluster5": 0.190060555935
        },
        "probability": 0.346445262432,
        "value": "Cluster4"
    },
    "timbre": {
        "all": {
            "bright": 0.00181935401633,
            "dark": 0.998180627823
        },
        "probability": 0.998180627823,
        "value": "dark"
    },
    "tonal_atonal": {
        "all": {
            "atonal": 0.999999940395,
            "tonal": 8.40525729018e-08
        },
        "probability": 0.999999940395,
        "value": "atonal"
    },
    "voice_instrumental": {
        "all": {
            "instrumental": 0.565773785114,
            "voice": 0.434226185083
        },
        "probability": 0.565773785114,
        "value": "instrumental"
    }
},
"lowlevel": {
    "average_loudness": 0.911305367947,
    "barkbands_crest": {
        "dmean": 2.03161716461,
        "dmean2": 3.36738371849,
        "dvar": 7.08670473099,
        "dvar2": 17.1789093018,
        "max": 26.4700698853,
        "mean": 16.830947876,
        "median": 18.5731201172,
        "min": 2.49523591995,
        "stdev": 5.6197924614,
        "var": 31.5820655823
    },
    "barkbands_flatness_db": {
        "dmean": 0.0229827221483,
        "dmean2": 0.034576062113,
        "dvar": 0.000763663847465,
        "dvar2": 0.00156699831132,
        "max": 0.539493918419,
        "mean": 0.228437423706,
        "median": 0.231241673231,
        "min": 0.0392637252808,
        "stdev": 0.0663394629955,
        "var": 0.00440092477947
    },
    "barkbands_kurtosis": {
        "dmean": 7.01723146439,
        "dmean2": 11.0924749374,
        "dvar": 143.379379272,
        "dvar2": 334.678192139,
        "max": 239.180938721,
        "mean": 18.4999237061,
        "median": 9.65336418152,
        "min": -1.96328139305,
        "stdev": 23.8903675079,
        "var": 570.749694824
    },
    "barkbands_skewness": {
        "dmean": 0.729832410812,
        "dmean2": 1.1207818985,
        "dvar": 0.788796901703,
        "dvar2": 1.72652697563,
        "max": 14.4006204605,
        "mean": 3.29058361053,
        "median": 2.87227058411,
        "min": -7.25327825546,
        "stdev": 2.35867929459,
        "var": 5.56336832047
    },
    "barkbands_spread": {
        "dmean": 3.47077655792,
        "dmean2": 5.28425931931,
        "dvar": 21.8490962982,
        "dvar2": 40.328453064,
        "max": 75.5467681885,
        "mean": 12.7831611633,
        "median": 10.3342208862,
        "min": 0.4611094594,
        "stdev": 9.93517112732,
        "var": 98.7076339722
    },
    "dissonance": {
        "dmean": 0.023565961048,
        "dmean2": 0.0404973402619,
        "dvar": 0.000582534587011,
        "dvar2": 0.00164855504408,
        "max": 0.499999940395,
        "mean": 0.461437374353,
        "median": 0.469301730394,
        "min": 0.138476714492,
        "stdev": 0.0320512466133,
        "var": 0.00102728244383
    },
    "dynamic_complexity": 4.33110523224,
    "erbbands_crest": {
        "dmean": 3.0566213131,
        "dmean2": 4.98190641403,
        "dvar": 9.38768577576,
        "dvar2": 22.1358852386,
        "max": 32.5199203491,
        "mean": 11.5085487366,
        "median": 9.81259059906,
        "min": 2.38767528534,
        "stdev": 5.94076681137,
        "var": 35.2927093506
    },
    "erbbands_flatness_db": {
        "dmean": 0.0191546157002,
        "dmean2": 0.0293817985803,
        "dvar": 0.00037427758798,
        "dvar2": 0.000813583785202,
        "max": 0.594393610954,
        "mean": 0.170271828771,
        "median": 0.160062551498,
        "min": 0.0579863972962,
        "stdev": 0.0676463246346,
        "var": 0.0045760255307
    },
    "erbbands_kurtosis": {
        "dmean": 1.3731020689,
        "dmean2": 2.25455546379,
        "dvar": 6.72128009796,
        "dvar2": 18.5365772247,
        "max": 58.2980918884,
        "mean": 1.45432591438,
        "median": 0.631987690926,
        "min": -1.86052072048,
        "stdev": 2.8897562027,
        "var": 8.35069084167
    },
    "erbbands_skewness": {
        "dmean": 0.412955701351,
        "dmean2": 0.648366987705,
        "dvar": 0.203618556261,
        "dvar2": 0.486128747463,
        "max": 4.2663269043,
        "mean": -0.191611021757,
        "median": -0.220988482237,
        "min": -4.5537610054,
        "stdev": 0.853040635586,
        "var": 0.727678358555
    },
    "erbbands_spread": {
        "dmean": 7.63226985931,
        "dmean2": 12.1467370987,
        "dvar": 72.0115737915,
        "dvar2": 167.527328491,
        "max": 150.997756958,
        "mean": 34.1450653076,
        "median": 32.4563980103,
        "min": 0.602964162827,
        "stdev": 16.9642066956,
        "var": 287.784332275
    },
    "hfc": {
        "dmean": 6.72863769531,
        "dmean2": 9.91519737244,
        "dvar": 171.341705322,
        "dvar2": 277.654296875,
        "max": 187.272735596,
        "mean": 21.3778781891,
        "median": 14.4940233231,
        "min": 1.08955925883e-16,
        "stdev": 24.0800285339,
        "var": 579.84777832
    },
    "loudness_ebu128": {
        "integrated": -9.88048458099,
        "loudness_range": 9.85380077362,
        "momentary": {
            "dmean": 0.379715502262,
            "dmean2": 0.476796984673,
            "dvar": 0.529617488384,
            "dvar2": 0.83896958828,
            "max": -6.43911933899,
            "mean": -12.4630937576,
            "median": -9.49070549011,
            "min": -101.461555481,
            "stdev": 8.40561008453,
            "var": 70.6542739868
        },
        "short_term": {
            "dmean": 0.0866966471076,
            "dmean2": 0.0510203801095,
            "dvar": 0.0383617542684,
            "dvar2": 0.043859899044,
            "max": -7.24903249741,
            "mean": -11.7722587585,
            "median": -9.25111103058,
            "min": -59.4163894653,
            "stdev": 5.88517713547,
            "var": 34.635307312
        }
    },
    "melbands_crest": {
        "dmean": 2.49410367012,
        "dmean2": 3.98191213608,
        "dvar": 14.1453266144,
        "dvar2": 27.2215099335,
        "max": 38.0305709839,
        "mean": 25.0593833923,
        "median": 29.5003910065,
        "min": 1.91307854652,
        "stdev": 10.4761533737,
        "var": 109.749794006
    },
    "melbands_flatness_db": {
        "dmean": 0.0231004096568,
        "dmean2": 0.0348268710077,
        "dvar": 0.000874557998031,
        "dvar2": 0.00171136949211,
        "max": 0.565110623837,
        "mean": 0.305017381907,
        "median": 0.31209397316,
        "min": 0.00408373354003,
        "stdev": 0.0758021846414,
        "var": 0.00574597064406
    },
    "melbands_kurtosis": {
        "dmean": 18.4348258972,
        "dmean2": 29.0579967499,
        "dvar": 1163.79431152,
        "dvar2": 2557.2434082,
        "max": 768.678955078,
        "mean": 49.3140678406,
        "median": 25.2626419067,
        "min": -1.8962572813,
        "stdev": 65.0007324219,
        "var": 4225.09472656
    },
    "melbands_skewness": {
        "dmean": 1.09118044376,
        "dmean2": 1.68891751766,
        "dvar": 1.84135460854,
        "dvar2": 3.86462855339,
        "max": 24.8377571106,
        "mean": 5.2681145668,
        "median": 4.48745441437,
        "min": -5.22626924515,
        "stdev": 3.42166233063,
        "var": 11.7077732086
    },
    "melbands_spread": {
        "dmean": 3.80226492882,
        "dmean2": 5.79994487762,
        "dvar": 39.1741294861,
        "dvar2": 80.6433410645,
        "max": 193.798416138,
        "mean": 12.1329879761,
        "median": 7.74358081818,
        "min": 0.496538460255,
        "stdev": 14.985751152,
        "var": 224.572738647
    },
    "pitch_salience": {
        "dmean": 0.0716589540243,
        "dmean2": 0.116400137544,
        "dvar": 0.00888768024743,
        "dvar2": 0.022338790819,
        "max": 0.992157876492,
        "mean": 0.33310765028,
        "median": 0.273562192917,
        "min": 0.0151909533888,
        "stdev": 0.198343411088,
        "var": 0.039340108633
    },
    "silence_rate_20dB": {
        "dmean": 0,
        "dmean2": 0,
        "dvar": 0,
        "dvar2": 0,
        "max": 1,
        "mean": 1,
        "median": 1,
        "min": 1,
        "stdev": 0,
        "var": 0
    },
    "silence_rate_30dB": {
        "dmean": 0.0269042924047,
        "dmean2": 0.0538131967187,
        "dvar": 0.0261803716421,
        "dvar2": 0.0697589144111,
        "max": 1,
        "mean": 0.358207672834,
        "median": 0,
        "min": 0,
        "stdev": 0.479463100433,
        "var": 0.229884877801
    },
    "silence_rate_60dB": {
        "dmean": 0.00993916578591,
        "dmean2": 0.0198800340295,
        "dvar": 0.00984074641019,
        "dvar2": 0.0258272718638,
        "max": 1,
        "mean": 0.0393248796463,
        "median": 0,
        "min": 0,
        "stdev": 0.194366618991,
        "var": 0.0377783812582
    },
    "spectral_centroid": {
        "dmean": 216.422805786,
        "dmean2": 329.010314941,
        "dvar": 67051.53125,
        "dvar2": 142753.6875,
        "max": 11493.5429688,
        "mean": 1282.11071777,
        "median": 1268.90588379,
        "min": 174.806564331,
        "stdev": 642.514404297,
        "var": 412824.75
    },
    "spectral_complexity": {
        "dmean": 3.18156123161,
        "dmean2": 4.73658943176,
        "dvar": 20.970998764,
        "dvar2": 34.1679267883,
        "max": 66,
        "mean": 15.6605548859,
        "median": 13,
        "min": 0,
        "stdev": 10.8633384705,
        "var": 118.012115479
    },
    "spectral_decrease": {
        "dmean": 2.62936561413e-09,
        "dmean2": 4.10107459103e-09,
        "dvar": 1.5271468026e-17,
        "dvar2": 3.82156648906e-17,
        "max": 1.8968534222e-20,
        "mean": -2.40990605249e-08,
        "median": -3.20448094726e-08,
        "min": -6.93692072673e-08,
        "stdev": 1.6807055303e-08,
        "var": 2.82477096989e-16
    },
    "spectral_energy": {
        "dmean": 0.0101159065962,
        "dmean2": 0.01584649086,
        "dvar": 0.000223903771257,
        "dvar2": 0.000563813198823,
        "max": 0.264962613583,
        "mean": 0.0928940996528,
        "median": 0.123435378075,
        "min": 1.02797579819e-20,
        "stdev": 0.0646259114146,
        "var": 0.00417650816962
    },
    "spectral_energyband_high": {
        "dmean": 0.000340853381203,
        "dmean2": 0.000525668088812,
        "dvar": 6.16482736859e-07,
        "dvar2": 1.11437407213e-06,
        "max": 0.0105353593826,
        "mean": 0.000697298441082,
        "median": 0.000172896194272,
        "min": 7.33330105814e-21,
        "stdev": 0.00130396184977,
        "var": 1.70031660218e-06
    },
    "spectral_energyband_low": {
        "dmean": 0.00895757414401,
        "dmean2": 0.0131203113124,
        "dvar": 0.000182165400474,
        "dvar2": 0.000383466569474,
        "max": 0.210482254624,
        "mean": 0.0803443193436,
        "median": 0.107397004962,
        "min": 4.69480691204e-23,
        "stdev": 0.0590735636652,
        "var": 0.00348968594335
    },
    "spectral_energyband_middle_high": {
        "dmean": 0.00316347531043,
        "dmean2": 0.00457053538412,
        "dvar": 3.23135973304e-05,
        "dvar2": 5.97888611082e-05,
        "max": 0.0799064561725,
        "mean": 0.00728179188445,
        "median": 0.00319421174936,
        "min": 1.31070625273e-21,
        "stdev": 0.00977891124785,
        "var": 9.56271032919e-05
    },
    "spectral_energyband_middle_low": {
        "dmean": 0.00384158315137,
        "dmean2": 0.00693347817287,
        "dvar": 0.000102772108221,
        "dvar2": 0.000284961657599,
        "max": 0.13073554635,
        "mean": 0.00505499262363,
        "median": 0.00315565778874,
        "min": 2.43274807699e-22,
        "stdev": 0.00859243702143,
        "var": 7.38299713703e-05
    },
    "spectral_entropy": {
        "dmean": 0.170474216342,
        "dmean2": 0.261463493109,
        "dvar": 0.0395757071674,
        "dvar2": 0.0879699662328,
        "max": 9.81217288971,
        "mean": 7.46289110184,
        "median": 7.58282804489,
        "min": 3.96928262711,
        "stdev": 0.626536846161,
        "var": 0.392548382282
    },
    "spectral_flux": {
        "dmean": 0.0356657356024,
        "dmean2": 0.0531917139888,
        "dvar": 0.00336377648637,
        "dvar2": 0.00562564935535,
        "max": 0.455009043217,
        "mean": 0.0883051529527,
        "median": 0.0529954843223,
        "min": 6.66162888741e-11,
        "stdev": 0.0913705378771,
        "var": 0.00834857579321
    },
    "spectral_kurtosis": {
        "dmean": 1.88734328747,
        "dmean2": 3.22109103203,
        "dvar": 8.85974597931,
        "dvar2": 26.0603599548,
        "max": 115.154518127,
        "mean": 5.46998739243,
        "median": 3.65318512917,
        "min": -1.23966503143,
        "stdev": 8.42901706696,
        "var": 71.048324585
    },
    "spectral_rms": {
        "dmean": 0.000500847760122,
        "dmean2": 0.000788533652667,
        "dvar": 4.61072033886e-07,
        "dvar2": 1.07166351881e-06,
        "max": 0.0160779375583,
        "mean": 0.00839767605066,
        "median": 0.0109738223255,
        "min": 3.16686477389e-12,
        "stdev": 0.00448416452855,
        "var": 2.01077327802e-05
    },
    "spectral_rolloff": {
        "dmean": 208.794235229,
        "dmean2": 355.608154297,
        "dvar": 223342.328125,
        "dvar2": 467590.90625,
        "max": 19573.6816406,
        "mean": 613.596191406,
        "median": 172.265625,
        "min": 43.06640625,
        "stdev": 1223.58959961,
        "var": 1497171.375
    },
    "spectral_skewness": {
        "dmean": 0.220296621323,
        "dmean2": 0.366249710321,
        "dvar": 0.0581784471869,
        "dvar2": 0.159855619073,
        "max": 8.89167690277,
        "mean": 1.65166020393,
        "median": 1.50407385826,
        "min": -0.0513892024755,
        "stdev": 0.720410764217,
        "var": 0.518991708755
    },
    "spectral_spread": {
        "dmean": 593965.25,
        "dmean2": 930902.9375,
        "dvar": 914659475456,
        "dvar2": 2.07668917043e+12,
        "max": 41132708,
        "mean": 4358275,
        "median": 4058351.5,
        "min": 628615.1875,
        "stdev": 1672748.375,
        "var": 2.79808704512e+12
    },
    "spectral_strongpeak": {
        "dmean": 0.183783844113,
        "dmean2": 0.307634115219,
        "dvar": 0.229709759355,
        "dvar2": 0.536970853806,
        "max": 7.89695882797,
        "mean": 0.69684278965,
        "median": 0.577846646309,
        "min": 0,
        "stdev": 0.734781980515,
        "var": 0.539904534817
    },
    "zerocrossingrate": {
        "dmean": 0.00545836612582,
        "dmean2": 0.00683246459812,
        "dvar": 8.03468647064e-05,
        "dvar2": 0.000107228472189,
        "max": 0.79248046875,
        "mean": 0.0299004502594,
        "median": 0.02099609375,
        "min": 0.001953125,
        "stdev": 0.0447627454996,
        "var": 0.00200370349921
    },
    "barkbands": {
        "dmean": [0.00244259415194, 0.0100651914254, 0.00440080137923, 0.0019616605714, 0.00134233711287, 0.000313945871312, 0.000171981097083, 0.000307164824335, 0.000444686826086, 0.00100141658913, 0.000421978911618, 0.000493726402055, 0.00103304791264, 0.000368594744941, 0.000761605915613, 0.000272638193564, 0.000215182255488, 0.000131802240503, 0.000110869528726, 0.0001065686738, 9.02865795069e-05, 6.8532244768e-05, 7.24337005522e-05, 5.26394760527e-05, 4.4017629989e-05, 1.64182110893e-05, 7.95174798895e-07],
        "dmean2": [0.00337227503769, 0.0146850533783, 0.00808104034513, 0.00370203494094, 0.00243370421231, 0.000555074075237, 0.000293977442198, 0.000498274574056, 0.000713778892532, 0.00170638877898, 0.000645913241897, 0.000731541891582, 0.00153702765238, 0.000576819758862, 0.00124021840747, 0.00042650825344, 0.000348394096363, 0.000195606218767, 0.000167369275005, 0.000165229270351, 0.000134202477057, 0.000104667320556, 0.000119453339721, 8.35647369968e-05, 7.39379320294e-05, 2.75211732514e-05, 1.31830427108e-06],
        "dvar": [2.48441319854e-05, 0.000291005009785, 0.00018149803509, 3.99902164645e-05, 1.32055747599e-05, 6.24638573754e-07, 2.83171715409e-07, 7.10080826138e-07, 1.35363268328e-06, 5.04457102579e-06, 1.25609301449e-06, 2.44812986239e-06, 5.4736083257e-06, 1.0621911315e-06, 2.52437166637e-06, 7.81054154686e-07, 5.16977706866e-07, 1.61406731536e-07, 7.84909488516e-08, 8.79287753719e-08, 5.63365958328e-08, 2.57979166918e-08, 2.41540050183e-08, 1.28350121642e-08, 8.53424531044e-09, 1.24683630087e-09, 5.42987660043e-12],
        "dvar2": [3.66555650544e-05, 0.000659272132907, 0.000502272450831, 0.000114483293146, 3.59089572157e-05, 1.70356042872e-06, 7.02378088135e-07, 1.68203860085e-06, 3.05094181385e-06, 1.49604757098e-05, 2.63659967459e-06, 4.83325493406e-06, 1.1467414879e-05, 2.28139879255e-06, 6.42969280307e-06, 2.07730431612e-06, 1.25312192267e-06, 2.81185776885e-07, 1.40272845783e-07, 1.75362757204e-07, 1.08384966779e-07, 4.86778759523e-08, 5.624086441e-08, 2.7553708648e-08, 2.1652155624e-08, 3.18284998357e-09, 1.39265647625e-11],
        "max": [0.0436332710087, 0.185851633549, 0.133798599243, 0.0761606246233, 0.0493226721883, 0.0158954951912, 0.0151149909943, 0.0171679537743, 0.0277390256524, 0.0306809917092, 0.018895085901, 0.0302459821105, 0.0369005352259, 0.0171337164938, 0.0255131870508, 0.0155049050227, 0.0113120591268, 0.00548742199317, 0.00422526244074, 0.00392229063436, 0.00401189504191, 0.00222303066403, 0.00318323005922, 0.00161980825942, 0.00134058808908, 0.000666475389153, 8.88837457751e-05],
        "mean": [0.010500408709, 0.0663006901741, 0.00310121593066, 0.00161621230654, 0.00163349637296, 0.000376340118237, 0.000232528487686, 0.000447213446023, 0.000674211070873, 0.00153085181955, 0.000605082313996, 0.00061977369478, 0.00151177833322, 0.00049394130474, 0.00142176728696, 0.000352569739334, 0.000296437356155, 0.000200693379156, 0.00019813941617, 0.000183058931725, 0.000169169376022, 0.000130644009914, 0.000127573861391, 8.5736552137e-05, 6.175818271e-05, 2.21311329369e-05, 1.03273339391e-06],
        "median": [0.00642366334796, 0.0843060463667, 0.000227641081437, 0.000518482120242, 0.000839645392261, 0.000210678961594, 0.000108911961433, 0.000176880887011, 0.000262750545517, 0.000414955982706, 0.000198286419618, 0.000113210000563, 0.000395450915676, 0.000171069026692, 0.000294531608233, 7.87619210314e-05, 0.000100951896457, 4.75003034808e-05, 6.24311651336e-05, 4.59950097138e-05, 4.69139813504e-05, 3.52638671757e-05, 2.22882335947e-05, 1.48642930071e-05, 9.12608265935e-06, 2.22046173803e-06, 2.92709714245e-08],
        "min": [1.35405450026e-23, 6.70309941751e-24, 5.90005124334e-24, 3.30845482915e-24, 2.11711129196e-23, 1.96800301246e-23, 1.72742031567e-23, 1.30636312538e-23, 4.38357099267e-23, 5.52004534904e-23, 1.61249606132e-23, 2.72548981508e-23, 2.9741110045e-23, 3.90153627436e-23, 8.82715158103e-23, 1.41337292759e-22, 4.72037894269e-23, 1.73435449769e-22, 1.36203676288e-22, 2.20634348258e-22, 3.70036778207e-22, 4.0981962688e-22, 5.4396960162e-22, 6.34188682477e-22, 9.35196748841e-22, 1.4301988132e-21, 2.21327621941e-21],
        "stdev": [0.0122102685273, 0.0517560318112, 0.010587900877, 0.0048640249297, 0.00321783823892, 0.000697662355378, 0.00054706382798, 0.00100349390414, 0.00141648680437, 0.00300491740927, 0.00136389897671, 0.00198736437596, 0.00312047707848, 0.00120272464119, 0.00283852824941, 0.00101410166826, 0.000768302648794, 0.000558778992854, 0.000410240812926, 0.000409241562011, 0.000344018742908, 0.000247581396252, 0.000285798887489, 0.000177607973455, 0.000126961866044, 4.70267295896e-05, 3.2300406474e-06],
        "var": [0.000149090657942, 0.00267868675292, 0.000112103640276, 2.36587384279e-05, 1.03544834928e-05, 4.86732801619e-07, 2.99278809734e-07, 1.00699992345e-06, 2.00643489734e-06, 9.02952797333e-06, 1.86022032267e-06, 3.94961716665e-06, 9.73737678578e-06, 1.44654666201e-06, 8.05724266684e-06, 1.02840215277e-06, 5.90288948388e-07, 3.12233964905e-07, 1.68297532355e-07, 1.67478646063e-07, 1.18348893352e-07, 6.12965536106e-08, 8.16810015181e-08, 3.15445944921e-08, 1.61193138837e-08, 2.21151319479e-09, 1.04331621467e-11]
    },
    "erbbands": {
        "dmean": [0.68649917841, 1.65570294857, 4.73225879669, 5.97156858444, 5.54027700424, 4.5260682106, 2.85297632217, 2.59556555748, 2.49034070969, 2.8692843914, 8.73381900787, 9.40165996552, 9.35020160675, 43.7281761169, 14.5161743164, 23.8924179077, 50.726764679, 17.7431221008, 39.6231575012, 16.0208015442, 14.0269203186, 9.34084033966, 7.8937163353, 5.64039325714, 5.58110570908, 5.31351804733, 3.8767645359, 3.62656879425, 2.56483745575, 2.2124042511, 2.06482458115, 1.42310988903, 0.685792148113, 0.527378201485, 0.292721897364, 0.114696577191, 0.0210137013346, 0.00237356103025, 0.000135832509841, 1.42842218338e-05],
        "dmean2": [0.912928104401, 2.79915952682, 8.3776845932, 11.0564537048, 10.1197957993, 8.1329536438, 5.12037754059, 4.56877374649, 4.34818744659, 4.7671251297, 13.8582372665, 15.166475296, 15.7315883636, 71.5830993652, 20.8533649445, 34.6110687256, 75.833190918, 26.1446075439, 64.6506195068, 25.6340179443, 22.2331600189, 14.3137168884, 11.7406597137, 8.41226863861, 8.52785587311, 8.46417808533, 5.70030641556, 5.32070350647, 4.00195980072, 3.40035247803, 3.46655058861, 2.32472610474, 1.08997964859, 0.88510453701, 0.49033716321, 0.193933621049, 0.0347112417221, 0.00394251476973, 0.000219987123273, 2.230877908e-05],
        "dvar": [1.43333518505, 11.3978567123, 181.010818481, 346.273956299, 288.302703857, 152.973388672, 62.8544197083, 39.1606712341, 53.9465675354, 37.7715492249, 588.467773438, 611.27911377, 377.869689941, 10050.2138672, 1397.12084961, 5178.45898438, 13548.7265625, 2612.23828125, 5940.07324219, 872.929748535, 2281.66723633, 685.847900391, 581.338378906, 253.837036133, 189.796295166, 218.28666687, 105.683929443, 92.9428253174, 38.8609657288, 26.1876583099, 19.0508155823, 9.74879550934, 2.1063387394, 1.17759859562, 0.386451333761, 0.0617013610899, 0.00197804765776, 2.81955690298e-05, 1.45397834217e-07, 4.79878192738e-10],
        "dvar2": [2.45791316032, 29.8233032227, 482.075714111, 981.03918457, 773.691101074, 426.163452148, 171.787094116, 106.639160156, 140.321762085, 96.3448944092, 1357.52160645, 1459.03381348, 1004.02929688, 27312.3203125, 2726.98120117, 10107.0253906, 28646.3398438, 5193.11962891, 15186.3105469, 2058.44213867, 5657.47216797, 1375.69250488, 1042.6796875, 484.743225098, 347.976287842, 478.24420166, 190.414825439, 178.43057251, 77.8065795898, 53.2209815979, 46.2446060181, 22.1662387848, 4.47415161133, 2.98736453056, 0.984333217144, 0.161136865616, 0.00475501362234, 6.91320965416e-05, 3.47941750078e-07, 1.13761722265e-09],
        "max": [9.31388187408, 45.8857460022, 127.736541748, 212.707244873, 337.484649658, 191.200881958, 152.366012573, 118.983978271, 189.341491699, 124.003219604, 498.393676758, 534.10333252, 266.290039062, 1496.65795898, 697.545532227, 1525.20117188, 1852.12341309, 964.457763672, 1224.99841309, 372.261444092, 1025.79211426, 388.341918945, 349.161651611, 236.034927368, 211.914291382, 200.68006897, 152.323791504, 163.086288452, 84.4544067383, 130.374420166, 55.8298912048, 35.8213539124, 24.1857032776, 17.1262340546, 11.3710260391, 4.32086086273, 0.82062536478, 0.0870770290494, 0.0137803731486, 0.000481721246615],
        "mean": [3.53031992912, 8.31995677948, 4.77262067795, 4.63839864731, 5.73841047287, 5.53356409073, 3.33759450912, 3.18204522133, 3.06562876701, 4.67313718796, 13.099852562, 14.4750394821, 16.1748218536, 69.5813064575, 22.6798324585, 33.5343437195, 74.7779541016, 26.3019733429, 76.3333816528, 29.0253562927, 21.2248477936, 14.8367290497, 12.7180700302, 9.42039489746, 10.2646980286, 9.0389547348, 7.17822360992, 6.45149993896, 4.78565740585, 4.48391437531, 3.32737731934, 2.18671560287, 1.16858434677, 0.759786188602, 0.392553687096, 0.144814014435, 0.0316548459232, 0.00347722624429, 0.000235218001762, 0.000110875014798],
        "median": [4.52548599243, 6.60422849655, 0.877972006798, 1.3224196434, 2.7414624691, 2.89757919312, 1.67211723328, 1.80292344093, 1.2392834425, 2.58397221565, 4.743268013, 5.29872512817, 8.13736629486, 16.7839393616, 8.68279457092, 8.66191101074, 20.541601181, 9.66767787933, 22.033946991, 9.07182121277, 5.29038906097, 5.30027580261, 3.65167236328, 2.5383784771, 3.46391749382, 2.14250445366, 2.03259110451, 1.64763021469, 1.21098828316, 1.00370693207, 0.64265692234, 0.387222081423, 0.213887184858, 0.116241775453, 0.0538625493646, 0.0157121680677, 0.00314530637115, 0.000247856543865, 7.4298819527e-05, 0.000139532741741],
        "min": [2.39740786574e-22, 6.35356550026e-22, 7.41150032218e-21, 1.52230878734e-20, 2.12654774582e-20, 6.72058786046e-20, 9.19622440403e-20, 1.66762325677e-19, 2.47257261488e-19, 4.26929834425e-19, 5.21511681917e-19, 9.84772271122e-19, 1.08089562138e-18, 1.52428572961e-18, 2.1762580113e-18, 1.00914090857e-18, 1.54585922037e-18, 1.91571369593e-18, 4.29924600474e-18, 5.00000570914e-18, 6.72845998325e-18, 3.48577053416e-18, 8.35805542082e-18, 7.40245584535e-18, 7.22114281816e-18, 1.0731409479e-17, 1.30998368494e-17, 1.25638602084e-17, 1.30585216594e-17, 1.49945478092e-17, 1.60416492769e-17, 1.46264292756e-17, 9.16459704991e-18, 8.89800831901e-18, 7.51399453351e-18, 4.76284599649e-18, 2.84658181186e-18, 1.14837618858e-18, 3.02363413511e-19, 3.13859692449e-20],
        "stdev": [2.99193358421, 8.29948043823, 11.4575586319, 14.3355321884, 14.7503843307, 10.3568267822, 6.73031044006, 5.65380144119, 7.27005147934, 7.30628347397, 30.1349411011, 29.8733234406, 23.6210460663, 143.482711792, 48.8454780579, 92.2120895386, 153.571090698, 62.5649032593, 135.907867432, 47.4966850281, 62.0359535217, 33.9428634644, 33.208190918, 22.2102832794, 20.3082122803, 19.6391391754, 15.3238458633, 13.6202058792, 9.29970550537, 10.2939453125, 6.55586338043, 4.53579711914, 2.36447143555, 1.53597319126, 0.826518774033, 0.310558378696, 0.0672357678413, 0.00814162008464, 0.000573967117816, 7.96746098786e-05],
        "var": [8.95166683197, 68.8813705444, 131.275650024, 205.507476807, 217.57383728, 107.263870239, 45.297077179, 31.9654693604, 52.8536491394, 53.3817749023, 908.114624023, 892.415466309, 557.953796387, 20587.2871094, 2385.88061523, 8503.06933594, 23584.0800781, 3914.36694336, 18470.9492188, 2255.93505859, 3848.45947266, 1152.11804199, 1102.78405762, 493.296722412, 412.423461914, 385.695770264, 234.820251465, 185.510009766, 86.4845199585, 105.965309143, 42.979347229, 20.5734539032, 5.59072542191, 2.35921359062, 0.683133244514, 0.0964465066791, 0.00452064815909, 6.62859747536e-05, 3.29438250901e-07, 6.34804342425e-09]
    },
    "gfcc": {
        "mean": [-34.5653953552, 105.211395264, -114.489334106, 42.7875404358, -36.4573287964, 36.3978538513, -18.2208042145, 11.3553819656, -10.142996788, 3.39193177223, -11.823800087, -3.33391976357, 1.96885001659],
        "cov": [[19789.0820312, -691.485961914, 799.517456055, 1448.76806641, -168.494384766, 1221.29931641, 618.816894531, 872.465270996, -40.8542175293, 994.973876953, 790.131530762, 738.54675293, -475.586791992], [-691.485961914, 1734.67822266, 63.390209198, 257.667572021, -101.458259583, -543.002258301, -98.7967605591, -338.206237793, 81.4142074585, -346.532836914, -67.7108612061, -315.262908936, 118.029632568], [799.517456055, 63.390209198, 645.94317627, 274.848632812, -100.041648865, 4.35356330872, -2.07052063942, 66.5530700684, -8.60430526733, 49.6422119141, 34.8119354248, 40.6858444214, -84.3509597778], [1448.76806641, 257.667572021, 274.848632812, 490.765777588, -141.616134644, -111.813247681, -14.8154344559, 4.77294921875, 4.43404436111, -20.2527179718, 34.916053772, -24.1742267609, -33.2473983765], [-168.494384766, -101.458259583, -100.041648865, -141.616134644, 284.153594971, 193.987442017, 106.661125183, 49.6006393433, 56.6049842834, 72.1992034912, 44.0356826782, 32.0821304321, 40.0991706848], [1221.29931641, -543.002258301, 4.35356330872, -111.813247681, 193.987442017, 430.479614258, 187.496780396, 188.5262146, 26.247882843, 206.917358398, 121.636009216, 157.578796387, -24.8606433868], [618.816894531, -98.7967605591, -2.07052063942, -14.8154344559, 106.661125183, 187.496780396, 256.077056885, 128.593490601, 74.6416625977, 115.321662903, 140.185348511, 77.6943130493, 4.79960393906], [872.465270996, -338.206237793, 66.5530700684, 4.77294921875, 49.6006393433, 188.5262146, 128.593490601, 195.941589355, 55.7509422302, 136.535415649, 91.3073730469, 110.839080811, -29.6153659821], [-40.8542175293, 81.4142074585, -8.60430526733, 4.43404436111, 56.6049842834, 26.247882843, 74.6416625977, 55.7509422302, 143.712219238, 47.2394218445, 69.4527435303, 1.20447134972, 39.8049049377], [994.973876953, -346.532836914, 49.6422119141, -20.2527179718, 72.1992034912, 206.917358398, 115.321662903, 136.535415649, 47.2394218445, 226.448501587, 153.649200439, 128.811019897, -54.5502090454], [790.131530762, -67.7108612061, 34.8119354248, 34.916053772, 44.0356826782, 121.636009216, 140.185348511, 91.3073730469, 69.4527435303, 153.649200439, 238.565200806, 113.725921631, -45.4493255615], [738.54675293, -315.262908936, 40.6858444214, -24.1742267609, 32.0821304321, 157.578796387, 77.6943130493, 110.839080811, 1.20447134972, 128.811019897, 113.725921631, 151.648086548, -28.9798641205], [-475.586791992, 118.029632568, -84.3509597778, -33.2473983765, 40.0991706848, -24.8606433868, 4.79960393906, -29.6153659821, 39.8049049377, -54.5502090454, -45.4493255615, -28.9798641205, 125.730606079]],
        "icov": [[0.000222176022362, -0.000584573252127, 0.000405882397899, -0.000751599320211, 0.000520587956998, -0.00109809008427, 0.000299255363643, -0.000675810442772, 0.000448789884103, -0.000890055263881, 0.000577627622988, -0.000755844346713, 0.000415296846768], [-0.000584573252127, 0.00376806384884, -0.00172899325844, 0.00154776673298, -0.00209558010101, 0.00435672560707, -0.00186557346024, 0.00392519123852, -0.00210643978789, 0.00419370364398, -0.00367420422845, 0.00425344705582, -0.00183496472891], [0.000405882397899, -0.00172899325844, 0.00326897692867, -0.00253740395419, 0.00139062805101, -0.00260536442511, 0.000906877336092, -0.00198048702441, 0.000499871559441, -0.00227278121747, 0.00254153786227, -0.00299570593052, 0.00230462918989], [-0.000751599320211, 0.00154776673298, -0.00253740395419, 0.00598282506689, -0.000602462503593, 0.00393998809159, -0.000726950354874, 0.000639521633275, -0.000561463064514, 0.00287633389235, -0.0033449830953, 0.00411931006238, -0.00210061087273], [0.000520587956998, -0.00209558010101, 0.00139062805101, -0.000602462503593, 0.00868944544345, -0.00702020153403, 0.000216139378608, -0.000133152701892, -0.00078513158951, -0.00289224623702, 0.00202083424665, -0.000968219770584, 1.20488930406e-05], [-0.00109809008427, 0.00435672560707, -0.00260536442511, 0.00393998809159, -0.00702020153403, 0.0153518654406, -0.00450646271929, 0.00110260874499, 0.000358029152267, 0.00176282331813, -0.00274787214585, 0.0027651952114, -0.00294779846445], [0.000299255363643, -0.00186557346024, 0.000906877336092, -0.000726950354874, 0.000216139378608, -0.00450646271929, 0.0107046151534, -0.00714109186083, 0.00191072560847, -0.000572431192268, -0.00435175653547, 0.00208747247234, -0.00169644586276], [-0.000675810442772, 0.00392519123852, -0.00198048702441, 0.000639521633275, -0.000133152701892, 0.00110260874499, -0.00714109186083, 0.0231488905847, -0.0114477388561, 0.00247250450775, 0.00381485396065, -0.00656213192269, 0.00314850825816], [0.000448789884103, -0.00210643978789, 0.000499871559441, -0.000561463064514, -0.00078513158951, 0.000358029152267, 0.00191072560847, -0.0114477388561, 0.0187047049403, -0.00588577101007, -0.0058076614514, 0.00821109116077, -0.00726843252778], [-0.000890055263881, 0.00419370364398, -0.00227278121747, 0.00287633389235, -0.00289224623702, 0.00176282331813, -0.000572431192268, 0.00247250450775, -0.00588577101007, 0.0206948183477, -0.00847023632377, 0.000535071594641, 0.00171113200486], [0.000577627622988, -0.00367420422845, 0.00254153786227, -0.0033449830953, 0.00202083424665, -0.00274787214585, -0.00435175653547, 0.00381485396065, -0.0058076614514, -0.00847023632377, 0.0196675751358, -0.0157835930586, 0.00796667952091], [-0.000755844346713, 0.00425344705582, -0.00299570593052, 0.00411931006238, -0.000968219770584, 0.0027651952114, 0.00208747247234, -0.00656213192269, 0.00821109116077, 0.000535071594641, -0.0157835930586, 0.0311503075063, -0.00943526625633], [0.000415296846768, -0.00183496472891, 0.00230462918989, -0.00210061087273, 1.20488930406e-05, -0.00294779846445, -0.00169644586276, 0.00314850825816, -0.00726843252778, 0.00171113200486, 0.00796667952091, -0.00943526625633, 0.0162058901042]]
    },
    "melbands": {
        "dmean": [0.00413198349997, 0.00198562815785, 0.00100570253562, 0.000342174258549, 0.000115659539006, 5.74006371608e-05, 3.68204964616e-05, 3.50582595274e-05, 7.81792914495e-05, 5.75081758143e-05, 4.75377819384e-05, 0.00018317035574, 5.10408281116e-05, 5.6472425058e-05, 0.000101353412902, 8.06372627267e-05, 3.21333063766e-05, 5.83708533668e-05, 4.9800684792e-05, 1.69484828803e-05, 1.75027853402e-05, 1.0088907402e-05, 1.04298051156e-05, 6.02617137702e-06, 4.66082974526e-06, 4.87030411023e-06, 3.50802520188e-06, 3.78198046747e-06, 2.72565330306e-06, 1.96893779503e-06, 2.42891496782e-06, 1.60598142429e-06, 1.26469910811e-06, 1.35942275392e-06, 1.24625285025e-06, 1.14623344416e-06, 8.11798315681e-07, 4.94249263738e-07, 4.61835014676e-07, 4.63586985688e-07],
        "dmean2": [0.00560157652944, 0.00329653546214, 0.00184154277667, 0.000623577274382, 0.000206645243452, 0.000101197532786, 6.39575082459e-05, 5.80753294344e-05, 0.000124041835079, 9.31538743316e-05, 7.96260719653e-05, 0.000302314874716, 7.39651732147e-05, 8.54203972267e-05, 0.000153743603732, 0.000118830692372, 4.84367228637e-05, 9.53216585913e-05, 8.07810283732e-05, 2.61194327322e-05, 2.87135571853e-05, 1.57418962772e-05, 1.61709922395e-05, 9.33300361794e-06, 7.02779379935e-06, 7.72534895077e-06, 5.44490603716e-06, 6.11069435763e-06, 3.99030341214e-06, 2.99868588627e-06, 3.61370371138e-06, 2.54038263847e-06, 1.98975499188e-06, 2.11963902075e-06, 2.10039570447e-06, 1.94988047042e-06, 1.3197637827e-06, 7.72103589952e-07, 7.71624513618e-07, 7.80259597377e-07],
        "dvar": [4.75199231005e-05, 2.29556681006e-05, 9.18940077099e-06, 8.96342726264e-07, 1.02834810889e-07, 1.92283060585e-08, 1.32122766061e-08, 6.19086559794e-09, 4.93202563234e-08, 2.06322141594e-08, 9.92836568514e-09, 1.7576753919e-07, 1.59626658558e-08, 3.61562584317e-08, 5.21722398616e-08, 3.6094288447e-08, 1.03015747044e-08, 1.16808189787e-08, 1.14292149078e-08, 2.26799823366e-09, 4.41046799082e-09, 1.00714903084e-09, 8.71481997677e-10, 3.24908711047e-10, 1.71068714749e-10, 1.46837694781e-10, 8.3145330898e-11, 1.10012922383e-10, 4.89114720947e-11, 2.6958529159e-11, 4.18510226474e-11, 1.52118994484e-11, 7.67716879652e-12, 1.2474504936e-11, 6.74266632111e-12, 6.02296294436e-12, 3.18059077339e-12, 1.2096736373e-12, 8.74406070554e-13, 9.23624241325e-13],
        "dvar2": [9.2301692348e-05, 5.57356179343e-05, 2.56333914876e-05, 2.47114780905e-06, 2.78677219967e-07, 5.25072714197e-08, 3.35798411299e-08, 1.62022040229e-08, 1.11027659955e-07, 4.95712839665e-08, 2.62032902043e-08, 4.85722125632e-07, 2.94822122271e-08, 7.41115826486e-08, 1.14256458517e-07, 7.41734993426e-08, 2.11247517257e-08, 2.94867099626e-08, 2.87784107655e-08, 5.0886526104e-09, 1.10412168297e-08, 2.24642193736e-09, 1.6603961539e-09, 5.97075333619e-10, 3.53448159629e-10, 2.8959140641e-10, 1.69893224489e-10, 2.49280873721e-10, 8.8920981689e-11, 5.50616774397e-11, 8.44372627373e-11, 3.20216596295e-11, 1.58696215891e-11, 2.75287206225e-11, 1.65341178249e-11, 1.47225252822e-11, 7.32589683361e-12, 2.49545349662e-12, 2.15114905056e-12, 2.40497032011e-12],
        "max": [0.0618886463344, 0.0490086004138, 0.0344628766179, 0.0133597720414, 0.00627770042047, 0.00262965355068, 0.00315563892946, 0.0013515810715, 0.00399455893785, 0.00289084739052, 0.00133725267369, 0.00594178261235, 0.00239645689726, 0.0036817858927, 0.00332799018361, 0.00271668611094, 0.00182975979988, 0.00156111177057, 0.00164552521892, 0.00100839301012, 0.0014818070922, 0.000467033591121, 0.000534643302672, 0.000260255124886, 0.000197048226255, 0.000179831782589, 0.000143188022776, 0.000147240236402, 0.00012050101941, 7.79314868851e-05, 0.000113459071144, 6.05781242484e-05, 4.06985454902e-05, 9.67577652773e-05, 3.56160817319e-05, 3.12041993311e-05, 2.30889618251e-05, 2.129427412e-05, 1.41221062222e-05, 1.51322337842e-05],
        "mean": [0.0239188559353, 0.00477518606931, 0.000842239765916, 0.000406116218073, 0.00014276112779, 7.07549770596e-05, 4.65913435619e-05, 5.56659069844e-05, 0.000117030336696, 8.76942358445e-05, 7.64515571063e-05, 0.000288631621515, 7.91342317825e-05, 7.03221303411e-05, 0.000149999177665, 0.00011492890917, 4.18446397816e-05, 0.000109639193397, 9.0490837465e-05, 2.17807300942e-05, 2.47487751039e-05, 1.43532452057e-05, 1.58516013471e-05, 9.09379377845e-06, 7.12665314495e-06, 8.22915262688e-06, 6.10679717283e-06, 5.95171559326e-06, 4.66535811938e-06, 3.57822250407e-06, 3.92885021938e-06, 2.7592659535e-06, 2.2971269118e-06, 2.65906965069e-06, 1.96991459234e-06, 1.58005627782e-06, 1.21990035495e-06, 8.17966054001e-07, 7.15500220849e-07, 6.21566755399e-07],
        "median": [0.0321585051715, 0.00232953042723, 0.000284172419924, 0.000219440931687, 7.15039350325e-05, 4.04761376558e-05, 2.0288523956e-05, 2.95603058476e-05, 3.79026532755e-05, 3.50509071723e-05, 3.75368144887e-05, 6.86033017701e-05, 2.95313657261e-05, 1.35644004331e-05, 3.83541555493e-05, 3.03892429656e-05, 1.17826521091e-05, 3.71027490473e-05, 1.75686036528e-05, 5.92005926592e-06, 5.43293072042e-06, 5.23156768395e-06, 4.37404924014e-06, 2.20984475163e-06, 1.74609976966e-06, 2.51473511526e-06, 1.96480755221e-06, 1.22606149944e-06, 1.37122697197e-06, 8.59497163219e-07, 9.52451443936e-07, 6.5995834575e-07, 6.35773062641e-07, 4.64404820377e-07, 3.66384938388e-07, 2.95983966225e-07, 1.9504820159e-07, 1.53323640006e-07, 1.0786506266e-07, 8.80304327211e-08],
        "min": [4.06211222483e-24, 3.04490290882e-24, 3.50707324179e-24, 4.10785590214e-24, 3.60730235853e-24, 3.40738765021e-24, 3.97387339942e-24, 5.18114967864e-24, 4.35714186465e-24, 5.86672502554e-24, 4.89187083482e-24, 6.99663771579e-24, 4.85891104291e-24, 4.36702234749e-24, 3.14325078952e-24, 2.4721727339e-24, 3.61324997533e-24, 4.74458182635e-24, 5.00239182536e-24, 7.09484774305e-24, 5.83856071907e-24, 2.98683821024e-24, 5.40921331064e-24, 7.77584848556e-24, 4.75856162488e-24, 5.48492581374e-24, 5.23451809103e-24, 6.51639181847e-24, 8.99418577796e-24, 7.35570353402e-24, 6.10825609092e-24, 7.26517227881e-24, 8.15858170866e-24, 7.64487706491e-24, 9.27641891061e-24, 8.47304612017e-24, 7.40365602186e-24, 5.71711045512e-24, 7.02760208404e-24, 5.89475088692e-24],
        "stdev": [0.0190253406763, 0.00618804106489, 0.0023988946341, 0.000817778985947, 0.000274075428024, 0.000124821381178, 0.000115018767247, 9.26226566662e-05, 0.000278163410258, 0.000174101005541, 0.000119583972264, 0.000595664838329, 0.000168479804415, 0.000230625868426, 0.000302948144963, 0.00024505527108, 0.000119477292174, 0.000181468392839, 0.000187597222975, 5.76616002945e-05, 8.43498855829e-05, 3.63345279766e-05, 4.0151830035e-05, 2.46848321694e-05, 1.73786429514e-05, 1.70612092916e-05, 1.25403121274e-05, 1.35299042086e-05, 1.0347242096e-05, 7.45232682675e-06, 8.7534854174e-06, 5.58273268325e-06, 4.19771686211e-06, 7.40880568628e-06, 3.89969090975e-06, 3.16792193189e-06, 2.59740818365e-06, 1.7229721152e-06, 1.45544390762e-06, 1.28716158088e-06],
        "var": [0.000361963553587, 3.82918515243e-05, 5.75469539399e-06, 6.68762481837e-07, 7.51173416802e-08, 1.55803778767e-08, 1.32293163091e-08, 8.57895710027e-09, 7.73748851657e-08, 3.03111598043e-08, 1.43003271447e-08, 3.54816620529e-07, 2.83854451055e-08, 5.31882911048e-08, 9.17775722087e-08, 6.00520806415e-08, 1.42748239895e-08, 3.29307781044e-08, 3.51927162967e-08, 3.32486016497e-09, 7.11490288907e-09, 1.32019783994e-09, 1.61216939798e-09, 6.09340911062e-10, 3.02017216791e-10, 2.91084850668e-10, 1.57259427702e-10, 1.83058304626e-10, 1.07065425969e-10, 5.55371755528e-11, 7.662351309e-11, 3.11669058617e-11, 1.76208266728e-11, 5.48904047215e-11, 1.52075886606e-11, 1.00357291921e-11, 6.74652955029e-12, 2.96863293496e-12, 2.11831680669e-12, 1.65678484387e-12]
    },
    "melbands128": {
        "dmean": [0.00234577595256, 0.00727980816737, 0.0048360824585, 0.00295886443928, 0.00272591831163, 0.00201869662851, 0.00130019709468, 0.000896684301551, 0.000552933546714, 0.000343885272741, 0.000266168179223, 0.000156563619385, 9.90314365481e-05, 8.24067246867e-05, 6.92598259775e-05, 5.3577899962e-05, 4.66848905489e-05, 4.32908418588e-05, 3.49918300344e-05, 3.48243302142e-05, 4.29405990872e-05, 7.35323410481e-05, 0.000108049644041, 0.000110364555439, 8.29291457194e-05, 4.63421347376e-05, 6.42929080641e-05, 3.57042335963e-05, 5.32877529622e-05, 0.000268615811365, 0.000252239988185, 7.10521853762e-05, 5.70145675738e-05, 3.71159985662e-05, 6.35387841612e-05, 8.16552055767e-05, 7.61557603255e-05, 5.9897909523e-05, 0.000235084778978, 0.000139470037539, 4.74125627079e-05, 3.16305631713e-05, 3.67501343135e-05, 4.94920786878e-05, 4.43457829533e-05, 4.43943208666e-05, 0.000160766227054, 5.90341041971e-05, 1.35135942401e-05, 1.57186896104e-05, 1.93308005692e-05, 2.74890535366e-05, 2.60097185674e-05, 2.41348097916e-05, 1.56378391694e-05, 8.63741297508e-06, 1.01975711004e-05, 1.95069842448e-05, 1.03781949292e-05, 9.11623919819e-06, 7.48669390305e-06, 6.33284980722e-06, 5.97872440267e-06, 5.84660801906e-06, 5.04413674207e-06, 6.83848065819e-06, 6.02090722168e-06, 3.95808820031e-06, 4.25778898716e-06, 4.89271951665e-06, 4.77084768136e-06, 4.43024964625e-06, 3.49405354427e-06, 3.17867511512e-06, 3.13740520141e-06, 2.35460356635e-06, 2.13968860407e-06, 2.40076451519e-06, 3.40161545864e-06, 2.610908723e-06, 1.77566801085e-06, 1.83405836651e-06, 1.5434160332e-06, 1.60436991337e-06, 1.47047410337e-06, 1.43535851294e-06, 1.77293770776e-06, 1.32359662075e-06, 1.53658277213e-06, 1.26699637804e-06, 1.48837273173e-06, 1.29044087771e-06, 1.15879981877e-06, 8.94985589639e-07, 7.91186721472e-07, 5.741754876e-07, 5.48455886928e-07, 4.76418023254e-07, 5.26827875547e-07, 5.45064665403e-07, 4.87516103931e-07, 5.40296525742e-07, 4.63961555397e-07, 3.53408495357e-07, 3.38453531867e-07, 3.52611408516e-07, 4.1053826294e-07, 2.73370972081e-07, 1.72724980985e-07, 1.62630357181e-07, 1.31437104756e-07, 8.87217694867e-08, 6.09763191051e-08, 4.26877342363e-08, 3.59112206638e-08, 2.60691841447e-08, 1.59155355561e-08, 8.7613098998e-09, 7.25755278097e-09, 3.65706620542e-09, 2.39989317308e-09, 1.70108582775e-09, 1.27827437524e-09, 7.66361141213e-10, 4.63906441039e-10, 6.34465951999e-11, 1.14632140585e-11, 1.12211325301e-11],
        "dmean2": [0.00321328663267, 0.00964561384171, 0.0078070955351, 0.00513040041551, 0.00480505032465, 0.00372097198851, 0.00244761095382, 0.00168219697662, 0.00099887244869, 0.000626057619229, 0.0004779487208, 0.000280706386548, 0.000179292284884, 0.000145679601701, 0.000120694836369, 9.58760356298e-05, 8.26602918096e-05, 7.49273385736e-05, 5.85312918702e-05, 5.83638320677e-05, 7.33139022486e-05, 0.000121836361359, 0.0001706625917, 0.000178100104677, 0.000135736423545, 7.88714678492e-05, 0.000106882936961, 6.14482851233e-05, 8.90494484338e-05, 0.000461463874672, 0.000409120635595, 0.000115104252473, 8.5948886408e-05, 5.73053403059e-05, 0.000105302067823, 0.000129642896354, 0.00012506818166, 9.66667794273e-05, 0.000363348721294, 0.000216302156332, 7.28825980332e-05, 5.31620462425e-05, 5.84328627156e-05, 8.30700446386e-05, 7.48727034079e-05, 7.22466138541e-05, 0.000265657348791, 9.54636852839e-05, 2.24818741117e-05, 2.58642867266e-05, 3.2222673326e-05, 4.21415679739e-05, 4.68820617243e-05, 4.00370154239e-05, 2.69680967904e-05, 1.45444500959e-05, 1.61144816957e-05, 3.32605850417e-05, 1.5443756638e-05, 1.5680296201e-05, 1.18489433589e-05, 1.0465358173e-05, 9.92699551716e-06, 8.89411785465e-06, 8.57611939864e-06, 1.10150185719e-05, 9.78460957413e-06, 6.27205918136e-06, 7.12659721103e-06, 8.13515725895e-06, 8.11874724604e-06, 7.49542277845e-06, 5.17204352946e-06, 5.17520311405e-06, 4.981492566e-06, 3.78112463295e-06, 3.46220554093e-06, 3.77852143174e-06, 5.27802330907e-06, 4.13420775658e-06, 2.79320420304e-06, 3.09335018756e-06, 2.5279584861e-06, 2.63393644673e-06, 2.35483912547e-06, 2.24973723562e-06, 2.82630344373e-06, 2.20581546273e-06, 2.5959566301e-06, 2.1566659143e-06, 2.60867068391e-06, 2.22611720346e-06, 1.88697686099e-06, 1.50995174408e-06, 1.32846435008e-06, 8.84733481143e-07, 8.90197384251e-07, 8.08226559457e-07, 8.7216733391e-07, 9.28987390125e-07, 8.38056337216e-07, 9.22252411328e-07, 7.76405954639e-07, 6.06996763963e-07, 5.73310330765e-07, 5.91381251525e-07, 7.21717924534e-07, 4.70833612098e-07, 2.88651762048e-07, 2.77738791965e-07, 2.23243389996e-07, 1.4830335715e-07, 9.89113289052e-08, 7.18313302173e-08, 6.05594863146e-08, 4.34260485349e-08, 2.7590989049e-08, 1.49704320052e-08, 1.22947145798e-08, 6.0600049423e-09, 3.8683749537e-09, 2.7419286841e-09, 1.99878935625e-09, 1.21533538788e-09, 7.55079110348e-10, 1.07413800077e-10, 2.04439399437e-11, 2.00495713781e-11],
        "dvar": [2.28750559472e-05, 0.000174365341081, 8.08252007118e-05, 4.68750222353e-05, 5.70568590774e-05, 3.97166368202e-05, 1.76371595444e-05, 8.52097309689e-06, 3.00744841297e-06, 7.86888506354e-07, 5.96507902628e-07, 1.80301483965e-07, 7.4917188897e-08, 4.64859830629e-08, 2.81995315987e-08, 1.26674537526e-08, 1.06661159904e-08, 3.48104194359e-08, 1.7974736366e-08, 4.59564031274e-09, 2.00775343018e-08, 3.98617530095e-08, 1.16957991736e-07, 1.64779905276e-07, 5.65553932574e-08, 1.3073309546e-08, 3.19985247188e-08, 1.13682343539e-08, 1.46582364025e-08, 3.97235567107e-07, 4.31932932088e-07, 4.18283718773e-08, 2.39846453809e-08, 1.41189273606e-08, 5.3820123469e-08, 1.22379915979e-07, 1.25474230117e-07, 3.50417757033e-08, 3.26029692133e-07, 1.30668396991e-07, 3.03674987379e-08, 1.71868794752e-08, 2.73181886001e-08, 3.557792283e-08, 1.74041030476e-08, 1.22227019617e-08, 1.4521067726e-07, 1.85903221706e-08, 1.56912094429e-09, 1.44271383729e-09, 4.84551243574e-09, 1.06472262118e-08, 1.35129152312e-08, 1.84686346216e-08, 5.77967318449e-09, 6.61305288308e-10, 9.15253040024e-10, 2.93411117624e-09, 1.24955923386e-09, 1.07466169297e-09, 4.99672747623e-10, 3.79532960615e-10, 3.26123628103e-10, 3.65929758717e-10, 2.26910767953e-10, 2.89524265673e-10, 1.83136783516e-10, 1.24274965319e-10, 1.37041766823e-10, 1.77803605172e-10, 1.75948824954e-10, 1.81551038092e-10, 1.11749894061e-10, 6.38810393472e-11, 8.07511280065e-11, 4.17258276542e-11, 2.67344497235e-11, 4.36803267168e-11, 8.79640457696e-11, 4.53973907077e-11, 1.88603525159e-11, 1.98598412021e-11, 1.31222975194e-11, 1.24229576279e-11, 1.01548595921e-11, 1.45558669284e-11, 3.0253841099e-11, 8.12231965713e-12, 1.02297458698e-11, 8.04191695875e-12, 1.0904289624e-11, 7.73134247595e-12, 1.05705513787e-11, 3.67338451324e-12, 3.2809644758e-12, 2.28094669888e-12, 1.5593646166e-12, 1.16484231115e-12, 1.23242236728e-12, 1.33895531381e-12, 1.04442973367e-12, 1.30019345984e-12, 1.38167277099e-12, 5.43784147485e-13, 5.77320418034e-13, 5.96559314534e-13, 9.15458030562e-13, 3.67912243639e-13, 1.42245495439e-13, 1.24549770996e-13, 8.28589651861e-14, 3.82957554557e-14, 2.56001562857e-14, 8.8967004472e-15, 7.02170238593e-15, 3.63267528309e-15, 1.98679095196e-15, 1.49096126392e-15, 1.16605837772e-15, 2.04416750797e-16, 9.03157879735e-17, 5.7407016108e-17, 3.51461134427e-17, 1.13619088757e-17, 4.58226295619e-18, 8.71621537197e-20, 3.08121774194e-22, 2.96465262536e-22],
        "dvar2": [3.26470435539e-05, 0.00027698429767, 0.000198199340957, 0.00012219727796, 0.000150242995005, 0.000110757842776, 5.06411015522e-05, 2.39671189775e-05, 7.76923479862e-06, 2.2112969873e-06, 1.67235452864e-06, 4.93254560752e-07, 2.08817624525e-07, 1.27208195977e-07, 7.60297069746e-08, 3.59917855519e-08, 2.97899749313e-08, 8.91750673304e-08, 4.03254993842e-08, 1.20775025536e-08, 5.34441504385e-08, 1.00933142733e-07, 2.56219777839e-07, 3.48424521235e-07, 1.4181156871e-07, 3.21950999194e-08, 7.88573046862e-08, 2.88751618172e-08, 3.65827332871e-08, 1.18818513783e-06, 1.07358596324e-06, 9.84492061207e-08, 5.1477826446e-08, 3.08819210204e-08, 1.37196252581e-07, 2.66001876525e-07, 2.78249785879e-07, 9.31352275302e-08, 7.20974242086e-07, 2.89001235387e-07, 6.79671074977e-08, 4.53586608273e-08, 6.12622486074e-08, 9.60645394343e-08, 4.53834871905e-08, 2.82058341128e-08, 3.76643697564e-07, 4.39565503996e-08, 4.1523615657e-09, 3.46321216149e-09, 1.29934409898e-08, 2.19239275623e-08, 3.99387829475e-08, 4.52162396414e-08, 1.51857495467e-08, 1.7094357041e-09, 1.85151671772e-09, 7.78562814219e-09, 2.52040077697e-09, 2.92170532212e-09, 9.96934756969e-10, 9.24455678675e-10, 8.69933403091e-10, 8.20946866043e-10, 5.91522775206e-10, 6.36694030831e-10, 4.52257425954e-10, 2.82726009271e-10, 3.46384282368e-10, 4.24927426579e-10, 4.52907933379e-10, 4.54913939851e-10, 2.27232302419e-10, 1.75013586956e-10, 1.75913103528e-10, 9.60418619633e-11, 6.47024309131e-11, 9.37115315902e-11, 1.96686292253e-10, 1.0299648634e-10, 4.01250768722e-11, 5.12726562596e-11, 3.0931566336e-11, 3.02845769296e-11, 2.28436245614e-11, 3.45010027492e-11, 7.0767815219e-11, 2.07404319413e-11, 2.53446933579e-11, 2.06843465966e-11, 2.93130658635e-11, 2.01232502883e-11, 2.62334303586e-11, 9.4083239463e-12, 8.18304365241e-12, 4.94137977064e-12, 3.66534667201e-12, 3.03494078827e-12, 3.03709401378e-12, 3.45858693247e-12, 2.78916386515e-12, 3.41735342281e-12, 3.78929743486e-12, 1.42870784647e-12, 1.48596087692e-12, 1.55387703572e-12, 2.51493964543e-12, 9.89060612924e-13, 3.52894091987e-13, 3.32848413545e-13, 2.19751137859e-13, 9.50392176524e-14, 5.20515806835e-14, 2.28534300316e-14, 1.82726860173e-14, 8.76009266754e-15, 5.48985854741e-15, 3.91712885205e-15, 3.02066856771e-15, 5.19727822672e-16, 2.16907125107e-16, 1.35697179544e-16, 8.41120591108e-17, 2.6914192312e-17, 1.14214030141e-17, 2.32674274084e-19, 9.72546901944e-22, 9.41516521812e-22],
        "max": [0.0415148772299, 0.100517973304, 0.0875635966659, 0.0729247406125, 0.0617309510708, 0.0644862800837, 0.0471278764307, 0.0441052876413, 0.0421869233251, 0.0130817648023, 0.0148593084887, 0.00952151417732, 0.00537243159488, 0.00445816200227, 0.00320711033419, 0.00182543008123, 0.00181445118506, 0.00554774515331, 0.00407709134743, 0.0019173915498, 0.00280792522244, 0.00425418093801, 0.00627584429458, 0.0110300127417, 0.00406473735347, 0.0019640319515, 0.00437421398237, 0.0020701829344, 0.00184059457388, 0.0088211465627, 0.0124869588763, 0.00288033345714, 0.0033320011571, 0.00207048840821, 0.00451028672978, 0.00805038772523, 0.00821528024971, 0.00341931823641, 0.00807800330222, 0.00651170080528, 0.00254385359585, 0.00288903177716, 0.00337706576101, 0.0031692662742, 0.00338939065114, 0.00234768912196, 0.00628303037956, 0.00196051574312, 0.000651732552797, 0.000875527446624, 0.00166310346685, 0.00324278627522, 0.00296933762729, 0.00318154273555, 0.00143781618681, 0.000389402819565, 0.000475777545944, 0.00145328231156, 0.00056872528512, 0.000563210342079, 0.000317889032885, 0.000356243137503, 0.000330908776959, 0.000322327192407, 0.000260125205386, 0.000266950082732, 0.000250381068327, 0.000195465268916, 0.000253848091234, 0.000298783765174, 0.000196348133613, 0.000419793039327, 0.000188442747458, 0.000162960917805, 0.000147725761053, 0.000184554199222, 9.01914536371e-05, 0.000111480068881, 0.000193391912035, 0.000143585915794, 7.0777212386e-05, 6.61752637825e-05, 7.01687458786e-05, 5.30494289706e-05, 7.71005652496e-05, 0.000104722821561, 0.000152626234922, 5.91951429669e-05, 7.22131226212e-05, 5.44809263374e-05, 4.52755230071e-05, 3.62670834875e-05, 4.9348014727e-05, 3.16230216413e-05, 3.33868119924e-05, 3.41703853337e-05, 2.20685124077e-05, 1.96056898858e-05, 2.91733558697e-05, 2.09343324968e-05, 2.1321569875e-05, 1.56859769049e-05, 2.59254065895e-05, 1.40011661642e-05, 1.51022777573e-05, 1.93602609215e-05, 1.41182435982e-05, 1.2213017726e-05, 9.66599782259e-06, 5.99852955929e-06, 5.09060646436e-06, 3.55759766535e-06, 9.57141764957e-06, 2.50847415373e-06, 1.85466876701e-06, 1.07157825369e-06, 8.09352172837e-07, 2.03846343538e-06, 2.09436120713e-06, 4.63190417577e-07, 3.05958252511e-07, 2.7822187576e-07, 1.88788931155e-07, 1.01464848967e-07, 6.30844922966e-08, 8.62358362497e-09, 1.77316966665e-10, 1.76200928848e-10],
        "mean": [0.0101155294105, 0.0349472314119, 0.0262475721538, 0.00983569398522, 0.00283471890725, 0.00138713174965, 0.00091296446044, 0.0007972017047, 0.000552123703528, 0.00041077050264, 0.000303120556055, 0.000186909936019, 9.56976946327e-05, 9.11215101951e-05, 7.71817212808e-05, 5.67351889913e-05, 4.90281709062e-05, 4.4975829951e-05, 4.04712445743e-05, 5.20755456819e-05, 5.35511389899e-05, 9.44304047152e-05, 0.000134913076181, 0.000128203784698, 9.87628736766e-05, 6.1319769884e-05, 8.68953939062e-05, 3.80971723644e-05, 6.6850319854e-05, 0.000372261449229, 0.00038562604459, 8.96429337445e-05, 7.27966034901e-05, 4.44395300292e-05, 6.0605485487e-05, 8.76200865605e-05, 7.55737855798e-05, 6.53609677101e-05, 0.000315232930006, 0.000183139331057, 4.89451376779e-05, 3.44922555087e-05, 3.74867922801e-05, 4.55386725662e-05, 5.78116232646e-05, 5.82558714086e-05, 0.000288467272185, 9.15893178899e-05, 1.48990075104e-05, 1.89267557289e-05, 1.98161742446e-05, 3.01348172798e-05, 2.44344955718e-05, 2.70220298262e-05, 1.59016635735e-05, 9.62679951044e-06, 1.30875732793e-05, 2.46416693699e-05, 1.26526838358e-05, 9.55537416303e-06, 9.5319128377e-06, 7.81611015555e-06, 7.52865935283e-06, 7.10612994226e-06, 6.23769665253e-06, 9.44679140957e-06, 8.78895843925e-06, 5.64139054404e-06, 5.55907581656e-06, 6.42535997031e-06, 6.29986152489e-06, 5.83104247198e-06, 4.63341439172e-06, 4.61483023173e-06, 4.41150859842e-06, 3.59003570338e-06, 3.21938227898e-06, 3.46158753928e-06, 4.6103123168e-06, 3.77858668799e-06, 2.62594744527e-06, 2.54435849456e-06, 2.30999717132e-06, 2.37681888393e-06, 2.24376822189e-06, 2.46730269282e-06, 3.20534059028e-06, 1.91579647435e-06, 2.19484422814e-06, 1.60530294124e-06, 1.69817315054e-06, 1.54170345468e-06, 1.57117824529e-06, 1.20172126117e-06, 1.04946116153e-06, 8.27940255022e-07, 8.20272703095e-07, 6.84426993303e-07, 7.66875416502e-07, 7.15813484931e-07, 6.01339650075e-07, 6.39832876459e-07, 6.05304535384e-07, 4.45084992862e-07, 4.17022533838e-07, 4.19853904532e-07, 4.17838492695e-07, 3.0501351489e-07, 2.18850274791e-07, 1.91202872202e-07, 1.60315849485e-07, 1.17601246075e-07, 9.38368458492e-08, 5.98705014454e-08, 4.34847287067e-08, 3.23183400042e-08, 1.73325549468e-08, 8.47568415452e-09, 7.38526884092e-09, 4.20227452835e-09, 2.96721158755e-09, 2.11742556822e-09, 1.57404422829e-09, 9.41635325269e-10, 5.15989584393e-10, 6.36627139894e-11, 9.99066628038e-12, 9.63546777089e-12],
        "median": [0.0063621532172, 0.0439544357359, 0.0291142519563, 0.00555108301342, 0.000453860149719, 9.54584393185e-05, 0.000206947457627, 0.000290391384624, 0.000220605783397, 0.00021723624377, 0.000150171792484, 8.75904515851e-05, 3.66839412891e-05, 4.54836517747e-05, 3.93889931729e-05, 2.66367624135e-05, 1.81967952813e-05, 7.62644231145e-06, 1.38264931593e-05, 2.0127499738e-05, 2.07842858799e-05, 3.75336530851e-05, 4.514182001e-05, 2.41403904511e-05, 2.55767281487e-05, 2.06247477763e-05, 3.04946479446e-05, 1.12966827146e-05, 1.80427523446e-05, 9.93052817648e-05, 5.7095385273e-05, 2.72970864899e-05, 2.20475922106e-05, 6.29273017694e-06, 6.24271024208e-06, 1.74432298081e-05, 1.06395600596e-05, 7.26262078388e-06, 7.41929397918e-05, 4.76208588225e-05, 3.70647194359e-06, 5.33299453309e-06, 4.27941176895e-06, 7.59207432566e-06, 1.85817625606e-05, 1.42649723784e-05, 3.63076251233e-05, 1.12677535071e-05, 4.13690349887e-06, 5.5188575061e-06, 3.07868049276e-06, 3.93856134906e-06, 4.32518936577e-06, 4.73412865176e-06, 3.68061682821e-06, 3.36299353876e-06, 3.73577449864e-06, 5.94814173382e-06, 2.21593336391e-06, 2.01517377718e-06, 2.22580274567e-06, 1.57893816777e-06, 1.77746369445e-06, 1.28109502384e-06, 1.51540962179e-06, 2.17288061322e-06, 2.88245541924e-06, 1.6915012111e-06, 1.53868006691e-06, 9.79440756055e-07, 1.0886169548e-06, 1.2287281379e-06, 1.20481536214e-06, 1.36831613418e-06, 8.75672412803e-07, 7.56574763727e-07, 7.16830413694e-07, 7.40547534406e-07, 9.86531858871e-07, 8.13002316136e-07, 5.81376525588e-07, 5.27708266418e-07, 4.96540508266e-07, 5.51724951947e-07, 6.56496013107e-07, 4.21762450742e-07, 3.24041707245e-07, 2.85949397494e-07, 3.9263409235e-07, 2.80103250816e-07, 3.1711522297e-07, 2.37461335928e-07, 2.30734514162e-07, 1.71508332869e-07, 1.39612339467e-07, 1.48472310002e-07, 1.55561195925e-07, 9.93594966303e-08, 9.91444153442e-08, 1.04770762732e-07, 7.79944144824e-08, 7.63319718544e-08, 8.51518464628e-08, 5.95171911755e-08, 4.66189504778e-08, 4.66194869375e-08, 3.33428502586e-08, 3.31672218579e-08, 2.22170726261e-08, 1.47236365322e-08, 1.27887984647e-08, 8.9652338886e-09, 1.03790203099e-08, 4.66732430482e-09, 2.54176635295e-09, 1.2013785522e-09, 3.68347907731e-10, 1.15146496504e-10, 1.22720819618e-10, 5.76745907976e-11, 3.89864564243e-11, 2.98701480217e-11, 2.46174764601e-11, 1.54480161302e-11, 1.05791521376e-11, 4.65876556083e-12, 2.1267085315e-12, 1.98169172044e-12],
        "min": [3.05462561947e-24, 8.11364838872e-25, 1.31321566424e-24, 7.93477565757e-25, 3.42736673593e-24, 2.65929034341e-24, 3.29806119229e-24, 1.02982803366e-24, 8.07342535724e-25, 1.29275409147e-24, 2.7969120587e-24, 1.76160449859e-24, 1.12615613462e-24, 1.69087029945e-24, 3.42665321124e-24, 1.11274402012e-24, 3.37666625112e-24, 3.37174099806e-24, 2.37608395362e-24, 2.58629290233e-24, 4.06141211078e-24, 7.5156055409e-25, 2.70169477251e-24, 3.81974023373e-24, 4.84105872619e-24, 3.00071170977e-24, 5.80915494275e-25, 4.2740239298e-24, 3.76963573333e-24, 9.21694668696e-24, 1.55957140291e-24, 1.94320244834e-24, 1.45337721583e-24, 3.20903370319e-24, 3.83991416809e-24, 5.41976728348e-25, 1.37132799029e-24, 3.76948584976e-24, 3.66775474185e-24, 2.50609789435e-24, 1.35520613858e-24, 1.99452711934e-24, 3.96188468581e-24, 2.67212156046e-24, 2.25083828264e-24, 5.60649795671e-24, 6.96934549505e-24, 1.73285959049e-24, 2.74711245305e-24, 7.155163259e-24, 5.85159388452e-24, 6.04651668103e-24, 4.14640950673e-24, 2.10235237495e-24, 4.24886518338e-24, 2.73152337827e-24, 2.71970722798e-24, 3.90910910239e-24, 4.65073577762e-24, 5.55837507491e-24, 6.55142986443e-24, 5.06835597983e-24, 4.55880981633e-24, 3.20115574376e-24, 5.49878609985e-24, 4.80917849043e-24, 3.74884569861e-24, 5.24871877062e-24, 4.85636459991e-24, 4.29158989001e-24, 3.7288188868e-24, 5.66595203655e-24, 9.0972228451e-24, 7.30066313094e-24, 4.79852137403e-24, 6.44590157456e-24, 6.41819086311e-24, 2.8641977524e-24, 4.36937630843e-24, 3.199664205e-24, 6.73275979869e-24, 3.59904298486e-24, 7.6927498778e-24, 7.52136195753e-24, 6.20486749155e-24, 7.27377717357e-24, 7.27877539626e-24, 8.01808084828e-24, 7.59637710759e-24, 5.93547267571e-24, 7.74725779977e-24, 6.41466820474e-24, 7.49201080983e-24, 5.55643723809e-24, 5.6146875162e-24, 6.13312138108e-24, 6.26350865023e-24, 2.90165464312e-24, 5.64108201322e-24, 4.58615094645e-24, 6.21683096161e-24, 4.49493338225e-24, 4.11800775313e-24, 6.07139222639e-24, 7.58998338996e-24, 9.22345400057e-24, 6.30297615018e-24, 6.69610143242e-24, 6.86700104779e-24, 6.78440178899e-24, 5.23002040058e-24, 8.69904766977e-24, 9.4095888866e-24, 5.40395791929e-24, 8.61009334752e-24, 6.52322138175e-24, 7.52157337226e-24, 7.1456874618e-24, 8.51261143888e-24, 6.93105339785e-24, 7.39919028028e-24, 6.78420772921e-24, 8.28134029843e-24, 7.79782141721e-24, 5.57321552069e-24, 7.9742493698e-24, 8.82739691677e-24, 8.2304516703e-24],
        "stdev": [0.0117183374241, 0.0316070951521, 0.0224249698222, 0.0122816283256, 0.00678291125223, 0.00490848487243, 0.00316297914833, 0.00232936022803, 0.00159145495854, 0.000739158538636, 0.000632625306025, 0.000363966129953, 0.000227965399972, 0.000185811426491, 0.000152595457621, 9.99030889943e-05, 9.74533468252e-05, 0.000178821210284, 0.000140711665154, 8.14928571344e-05, 0.00015230900317, 0.000220352230826, 0.000408745894674, 0.000446517689852, 0.000255246734014, 0.000130697662826, 0.000197279223357, 0.000105192011688, 0.000148179606185, 0.0007629856118, 0.000947734864894, 0.000226304982789, 0.000180055765668, 0.000144784353324, 0.000229488170589, 0.000370771507733, 0.000359396217391, 0.000187404686585, 0.000708399573341, 0.000427955150371, 0.000189212703845, 0.000123866979266, 0.000168610000401, 0.000168105703779, 0.000129230611492, 0.000137661991175, 0.000667183543555, 0.000213034436456, 3.82049838663e-05, 4.30371910625e-05, 6.93397159921e-05, 0.000119750380691, 9.98593386612e-05, 0.000145302605233, 6.76846830174e-05, 2.55527975241e-05, 3.50167065335e-05, 6.63301398163e-05, 4.27084996772e-05, 3.22648156725e-05, 2.8300415579e-05, 2.18246150325e-05, 1.95112734218e-05, 2.16398766497e-05, 1.62768519658e-05, 2.17581891775e-05, 1.70441726368e-05, 1.30823600557e-05, 1.34412312036e-05, 1.57982467499e-05, 1.53337950906e-05, 1.6325049728e-05, 1.28021692944e-05, 1.04489681689e-05, 1.10914534162e-05, 8.80358584254e-06, 6.79437744111e-06, 8.16816736915e-06, 1.14021240734e-05, 8.82285166881e-06, 5.78236222282e-06, 5.50629238205e-06, 4.89828335049e-06, 4.61946365249e-06, 4.57631585959e-06, 6.86459907229e-06, 1.09532711576e-05, 4.32364367953e-06, 4.67431391371e-06, 3.32655940838e-06, 3.54796020474e-06, 3.2738300888e-06, 4.13292082158e-06, 2.59309263129e-06, 2.39476503339e-06, 2.044773737e-06, 1.76333333002e-06, 1.47422508689e-06, 1.7422161136e-06, 1.56878945745e-06, 1.27464136312e-06, 1.36620644753e-06, 1.49377581238e-06, 9.41747828165e-07, 9.37697507197e-07, 9.68578092397e-07, 1.01374052974e-06, 6.81968742811e-07, 5.19187381087e-07, 4.33085602936e-07, 3.6421954519e-07, 2.66060737886e-07, 2.66779437652e-07, 1.34859362788e-07, 1.05565867159e-07, 8.21818986196e-08, 5.57055344075e-08, 4.00778752407e-08, 3.50179405473e-08, 1.73890182253e-08, 1.28551986833e-08, 9.79027170445e-09, 7.20597492787e-09, 4.40960645776e-09, 2.48573583939e-09, 3.01969310668e-10, 1.67722693373e-11, 1.63013699761e-11],
        "var": [0.000137319424539, 0.000999008538201, 0.000502879265696, 0.000150838386617, 4.60078881588e-05, 2.40932240558e-05, 1.0004437172e-05, 5.42591897101e-06, 2.53272878581e-06, 5.46355352071e-07, 4.00214759111e-07, 1.3247134234e-07, 5.19682217259e-08, 3.452588615e-08, 2.32853754056e-08, 9.98062787971e-09, 9.49715506238e-09, 3.19770236956e-08, 1.97997724882e-08, 6.64108590342e-09, 2.31980337162e-08, 4.85551048257e-08, 1.67073210378e-07, 1.99378035859e-07, 6.51508997862e-08, 1.7081877246e-08, 3.89190937256e-08, 1.10653592955e-08, 2.19571969495e-08, 5.82147038131e-07, 8.98201335531e-07, 5.12139450848e-08, 3.24200790658e-08, 2.09625099501e-08, 5.26648236132e-08, 1.37471516837e-07, 1.29165641738e-07, 3.51205144966e-08, 5.01829958921e-07, 1.83145601795e-07, 3.58014489166e-08, 1.53430299576e-08, 2.84293300012e-08, 2.8259528051e-08, 1.6700550276e-08, 1.8950823133e-08, 4.4513384978e-07, 4.53836683789e-08, 1.45962086862e-09, 1.85219983795e-09, 4.80799666747e-09, 1.4340153065e-08, 9.97188820406e-09, 2.11128483585e-08, 4.58121585112e-09, 6.52945475466e-10, 1.22616972131e-09, 4.39968728116e-09, 1.82401604931e-09, 1.04101827159e-09, 8.00913502186e-10, 4.76313821718e-10, 3.80689813007e-10, 4.68284244715e-10, 2.64935934302e-10, 4.73418804159e-10, 2.90503815448e-10, 1.71148137329e-10, 1.80666689942e-10, 2.49584575229e-10, 2.35125252601e-10, 2.66507260704e-10, 1.63895536032e-10, 1.09180942065e-10, 1.23020343912e-10, 7.75031289146e-11, 4.61635625559e-11, 6.67189567483e-11, 1.30008434573e-10, 7.78427183823e-11, 3.3435712532e-11, 3.03192575213e-11, 2.39931807061e-11, 2.13394441007e-11, 2.09426677389e-11, 4.71227223908e-11, 1.1997415561e-10, 1.86938936553e-11, 2.1849211676e-11, 1.1065997077e-11, 1.25880209034e-11, 1.07179638428e-11, 1.70810327688e-11, 6.72412993341e-12, 5.73489996811e-12, 4.18109991074e-12, 3.10934459603e-12, 2.17333963326e-12, 3.03531678958e-12, 2.46110033394e-12, 1.62471056574e-12, 1.86651995943e-12, 2.23136613353e-12, 8.86888978056e-13, 8.79276631973e-13, 9.38143443138e-13, 1.02766981123e-12, 4.65081369683e-13, 2.69555536746e-13, 1.87563140475e-13, 1.32655876301e-13, 7.07883120068e-14, 7.11712657667e-14, 1.81870459041e-14, 1.11441516009e-14, 6.75386421526e-15, 3.10310668457e-15, 1.6062360953e-15, 1.22625626812e-15, 3.02377924327e-16, 1.65256141244e-16, 9.58494145132e-17, 5.19260743558e-17, 1.94446273035e-17, 6.17888283864e-18, 9.1185463284e-20, 2.81309035736e-22, 2.65734649547e-22]
    },
    "mfcc": {
        "mean": [-673.316040039, 127.812232971, 1.06476807594, 25.0321311951, 11.9430713654, 26.1039943695, 11.771777153, 15.0823001862, 12.5911931992, 14.79500103, 3.45035529137, -1.72613477707, -0.20572629571],
        "cov": [[13353.9628906, -614.40057373, 84.989074707, -78.5045318604, 383.320159912, 686.545471191, 831.296264648, 533.768371582, 121.107780457, 139.653121948, 748.553161621, 1078.75744629, 572.989440918], [-614.40057373, 1371.70666504, 122.503677368, 383.193511963, -21.1662311554, -72.9043960571, -170.962295532, -71.3639297485, -42.3558120728, -10.4731636047, -86.1670227051, -142.462371826, -123.07585144], [84.989074707, 122.503677368, 464.403686523, 201.844360352, 16.9500331879, -57.2430648804, -79.0301437378, -6.09735012054, -31.7261962891, -8.77251815796, -5.51663732529, -34.7212638855, -40.8932647705], [-78.5045318604, 383.193511963, 201.844360352, 423.628173828, -13.5808010101, -102.279579163, -144.335327148, -42.9792709351, -15.9260587692, -31.1307964325, -70.2962265015, -76.3159790039, -72.2663421631], [383.320159912, -21.1662311554, 16.9500331879, -13.5808010101, 147.829864502, 67.7566452026, 36.3093147278, 27.5108718872, 24.7985153198, 17.2984924316, 17.1067008972, 39.675907135, 41.5381813049], [686.545471191, -72.9043960571, -57.2430648804, -102.279579163, 67.7566452026, 165.972595215, 146.134567261, 52.4619407654, 29.3183135986, 37.8712882996, 80.6061248779, 91.2345733643, 66.7455444336], [831.296264648, -170.962295532, -79.0301437378, -144.335327148, 36.3093147278, 146.134567261, 229.166885376, 91.6857910156, 26.8239307404, 37.7217102051, 120.275619507, 141.964263916, 90.2803115845], [533.768371582, -71.3639297485, -6.09735012054, -42.9792709351, 27.5108718872, 52.4619407654, 91.6857910156, 114.163421631, 57.3449516296, 36.3666610718, 56.8471641541, 69.8163070679, 44.2908554077], [121.107780457, -42.3558120728, -31.7261962891, -15.9260587692, 24.7985153198, 29.3183135986, 26.8239307404, 57.3449516296, 122.102767944, 70.1898727417, -12.5408115387, -31.1546726227, 8.59218120575], [139.653121948, -10.4731636047, -8.77251815796, -31.1307964325, 17.2984924316, 37.8712882996, 37.7217102051, 36.3666610718, 70.1898727417, 110.750984192, 32.4262123108, -17.5552711487, 9.28887748718], [748.553161621, -86.1670227051, -5.51663732529, -70.2962265015, 17.1067008972, 80.6061248779, 120.275619507, 56.8471641541, -12.5408115387, 32.4262123108, 207.653518677, 228.562286377, 92.4217834473], [1078.75744629, -142.462371826, -34.7212638855, -76.3159790039, 39.675907135, 91.2345733643, 141.964263916, 69.8163070679, -31.1546726227, -17.5552711487, 228.562286377, 375.403137207, 159.519195557], [572.989440918, -123.07585144, -40.8932647705, -72.2663421631, 41.5381813049, 66.7455444336, 90.2803115845, 44.2908554077, 8.59218120575, 9.28887748718, 92.4217834473, 159.519195557, 128.081497192]],
        "icov": [[0.000129679159727, 4.58131326013e-05, -2.27344899031e-05, -0.000192157604033, -6.16345496383e-05, -0.0003151515848, -9.15693090064e-05, -0.000310325296596, 9.56218209467e-05, -5.0202026614e-05, 1.61663569997e-06, -0.000189141501323, -6.40910657239e-05], [4.58131326013e-05, 0.00110345578287, 0.000250624725595, -0.0010922368383, 4.82740579173e-05, -0.000931153655984, 0.000633957737591, -0.000412284833146, 0.000789071549661, -0.000513351405971, -0.000106293337012, 4.41862503067e-05, 0.000490397040267], [-2.27344899031e-05, 0.000250624725595, 0.00312204496004, -0.00152932992205, -0.000852875935379, 0.000246430310654, 0.000833563623019, -0.00141505675856, 0.00163181952666, -0.000382539263228, -0.00140691688284, 0.000998943811283, 0.000215753359953], [-0.000192157604033, -0.0010922368383, -0.00152932992205, 0.00496441079304, -9.50393514358e-05, 0.00159529340453, 0.000948477594648, 0.000830399105325, -0.00158781232312, 0.000865298614372, 0.000770792132244, -0.000815598352347, 0.000869982352015], [-6.16345496383e-05, 4.82740579173e-05, -0.000852875935379, -9.50393514358e-05, 0.00996656622738, -0.00584193971008, 0.00287742167711, -0.00115044997074, -0.000321218045428, -0.000684179016389, 0.0025301638525, -0.00104050594382, -0.00228076474741], [-0.0003151515848, -0.000931153655984, 0.000246430310654, 0.00159529340453, -0.00584193971008, 0.0197746008635, -0.011169731617, 0.00469189928845, -0.00275201746263, -0.000195353350136, -0.00203648675233, 0.00135673582554, -0.000687172811013], [-9.15693090064e-05, 0.000633957737591, 0.000833563623019, 0.000948477594648, 0.00287742167711, -0.011169731617, 0.0172562710941, -0.00804682821035, 0.00292634684592, -0.000196126988158, -0.00248952629045, 0.00075243919855, -0.00199587293901], [-0.000310325296596, -0.000412284833146, -0.00141505675856, 0.000830399105325, -0.00115044997074, 0.00469189928845, -0.00804682821035, 0.0206501763314, -0.0103931557387, 0.0016837461153, -0.00119619723409, -0.00134589383379, 0.000582481618039], [9.56218209467e-05, 0.000789071549661, 0.00163181952666, -0.00158781232312, -0.000321218045428, -0.00275201746263, 0.00292634684592, -0.0103931557387, 0.0210529081523, -0.0121867796406, 0.00627285754308, -0.000844583497383, -0.000977830146439], [-5.0202026614e-05, -0.000513351405971, -0.000382539263228, 0.000865298614372, -0.000684179016389, -0.000195353350136, -0.000196126988158, 0.0016837461153, -0.0121867796406, 0.0220075007528, -0.0126865906641, 0.00884354114532, -0.00266118114814], [1.61663569997e-06, -0.000106293337012, -0.00140691688284, 0.000770792132244, 0.0025301638525, -0.00203648675233, -0.00248952629045, -0.00119619723409, 0.00627285754308, -0.0126865906641, 0.0253761168569, -0.016042156145, 0.00445338943973], [-0.000189141501323, 4.41862503067e-05, 0.000998943811283, -0.000815598352347, -0.00104050594382, 0.00135673582554, 0.00075243919855, -0.00134589383379, -0.000844583497383, 0.00884354114532, -0.016042156145, 0.0174265895039, -0.0104000298306], [-6.40910657239e-05, 0.000490397040267, 0.000215753359953, 0.000869982352015, -0.00228076474741, -0.000687172811013, -0.00199587293901, 0.000582481618039, -0.000977830146439, -0.00266118114814, 0.00445338943973, -0.0104000298306, 0.0214262176305]]
    },
    "spectral_contrast_coeffs": {
        "dmean": [0.0434819497168, 0.0407761447132, 0.0433719530702, 0.0341546088457, 0.0193138048053, 0.0181006230414],
        "dmean2": [0.0743268430233, 0.0672496259212, 0.0703783556819, 0.0543988086283, 0.0323214232922, 0.0285175498575],
        "dvar": [0.00188355182763, 0.00120956939645, 0.00126074138097, 0.000845436763484, 0.000255740713328, 0.00029163795989],
        "dvar2": [0.0054090321064, 0.00308482348919, 0.00309068569914, 0.00205690669827, 0.000673277943861, 0.000646339554805],
        "max": [-0.450733661652, -0.469138920307, -0.465807765722, -0.498616307974, -0.606300592422, -0.622474193573],
        "mean": [-0.737415611744, -0.793725669384, -0.743561387062, -0.748214483261, -0.809835791588, -0.765467226505],
        "median": [-0.74051040411, -0.798392832279, -0.750441014767, -0.753117799759, -0.811882972717, -0.762572526932],
        "min": [-0.971473753452, -0.980412423611, -0.971715867519, -0.971228301525, -0.965430855751, -0.964620351791],
        "stdev": [0.0642925351858, 0.0598030127585, 0.0687007755041, 0.0636690855026, 0.0328739695251, 0.0372380018234],
        "var": [0.00413353042677, 0.00357640022412, 0.00471979705617, 0.00405375240371, 0.00108069786802, 0.00138666888233]
    },
    "spectral_contrast_valleys": {
        "dmean": [0.381464093924, 0.354804068804, 0.364927202463, 0.319475144148, 0.22332406044, 0.310543805361],
        "dmean2": [0.624978125095, 0.588656544685, 0.592034161091, 0.500142991543, 0.339751750231, 0.45377177],
        "dvar": [0.196658462286, 0.12385109812, 0.150424972177, 0.128980889916, 0.0973536074162, 0.1859690696],
        "dvar2": [0.455873399973, 0.293757647276, 0.332315325737, 0.259237378836, 0.176145553589, 0.37420463562],
        "max": [-4.43527173996, -4.74093532562, -4.98796749115, -5.17183446884, -5.34711742401, -7.94121932983],
        "mean": [-6.76158666611, -7.29351949692, -7.73211336136, -7.9883723259, -7.98043394089, -10.6813220978],
        "median": [-6.50249004364, -7.06135559082, -7.50367164612, -7.66027164459, -7.75258350372, -10.4428405762],
        "min": [-27.6330909729, -28.1330699921, -27.5107135773, -27.3184986115, -27.391494751, -27.4135570526],
        "stdev": [1.63047301769, 1.44583714008, 1.4417924881, 1.49356913567, 1.47584831715, 1.62294411659],
        "var": [2.65844225883, 2.09044504166, 2.07876563072, 2.23074889183, 2.17812824249, 2.63394761086]
    }
},
"metadata": {
    "audio_properties": {
        "analysis": {
            "equal_loudness": 0,
            "length": 271.000091553,
            "sample_rate": 44100,
            "start_time": 0,
            "downmix": "mix"
        },
        "bit_rate": 1536000,
        "length": 271.000091553,
        "lossless": 1,
        "number_channels": 2,
        "replay_gain": -11.4500331879,
        "sample_rate": 48000,
        "codec": "pcm_s16le",
        "md5_encoded": "12f2eb560ed858e1badd3f72d7a85d67"
    },
    "tags": {
        "file_name": "TV_4_B4.wav"
    },
    "version": {
        "essentia": "2.1-beta5",
        "essentia_git_sha": "Undefined",
        "extractor": "music 2.0"
    }
},
"rhythm": {
    "beats_count": 401,
    "beats_loudness": {
        "dmean": 0.0246128328145,
        "dmean2": 0.0452840700746,
        "dvar": 0.000799694855232,
        "dvar2": 0.00208237278275,
        "max": 0.193790867925,
        "mean": 0.0901569575071,
        "median": 0.10912142694,
        "min": 1.48365954938e-11,
        "stdev": 0.0602890476584,
        "var": 0.00363476923667
    },
    "bpm": 80.0059280396,
    "bpm_histogram_first_peak_bpm": 80,
    "bpm_histogram_first_peak_weight": 0.0301724672318,
    "bpm_histogram_second_peak_bpm": 105,
    "bpm_histogram_second_peak_spread": 0.58490562439,
    "bpm_histogram_second_peak_weight": 0.165000006557,
    "danceability": 0.938711345196,
    "onset_rate": 3.61977005005,
    "beats_loudness_band_ratio": {
        "dmean": [0.141096100211, 0.0449964888394, 0.0182176530361, 0.0832201689482, 0.0528459921479, 0.0244819428772],
        "dmean2": [0.25218501687, 0.0769364833832, 0.0309181381017, 0.153841972351, 0.090396784246, 0.0461336113513],
        "dvar": [0.0252896361053, 0.00618156138808, 0.000470915721962, 0.0109102586284, 0.00472260965034, 0.00125646369997],
        "dvar2": [0.0689700767398, 0.0164262503386, 0.00119718257338, 0.0281997453421, 0.00983469653875, 0.00327633344568],
        "max": [0.985938668251, 0.622241199017, 0.138016760349, 0.772538483143, 0.971240401268, 0.300573647022],
        "mean": [0.699950516224, 0.102075189352, 0.0314432121813, 0.0893586575985, 0.0762609615922, 0.0262067783624],
        "median": [0.783924460411, 0.0125541072339, 0.0182850174606, 0.0500600934029, 0.0305605567992, 0.0117686726153],
        "min": [0, 0, 0, 0, 0, 0],
        "stdev": [0.254771232605, 0.161886155605, 0.03119783476, 0.106573648751, 0.130990788341, 0.0429300442338],
        "var": [0.0649083852768, 0.026207126677, 0.000973304850049, 0.0113579425961, 0.0171585883945, 0.00184298853856]
    },
    "beats_position": [0.777868449688, 1.55573689938, 2.31038546562, 3.06503391266, 3.8196823597, 4.57433080673, 5.32897949219, 6.08362817764, 6.83827638626, 7.59292507172, 8.33596324921, 9.0906124115, 9.84526062012, 10.5882987976, 11.3313379288, 12.0859861374, 12.840634346, 13.5836734772, 14.3267116547, 15.0697498322, 15.8243989944, 16.5790481567, 17.3220863342, 18.0651245117, 18.8081626892, 19.5628108978, 20.3174591064, 21.0721092224, 21.826757431, 22.5814056396, 23.3360538483, 24.0907020569, 24.8453502655, 25.4258499146, 26.0179595947, 26.6100673676, 27.2021770477, 27.7942848206, 28.3747844696, 28.9436721802, 29.5125617981, 30.0698413849, 30.6387290955, 31.2076187134, 31.7648983002, 32.322177887, 32.8794555664, 33.4483451843, 34.0172348022, 34.5861206055, 35.1550102234, 35.7122879028, 36.269569397, 36.8268470764, 37.3841247559, 37.94140625, 38.5102958679, 39.0791816711, 39.6364631653, 40.1937408447, 40.7510185242, 41.3199081421, 41.8771858215, 42.4460754395, 43.0033569336, 43.560634613, 44.129524231, 44.6984100342, 45.2556915283, 45.8129692078, 46.3818588257, 46.9507484436, 47.5196380615, 48.0885238647, 48.6458053589, 49.2030830383, 49.7603607178, 50.3292503357, 50.8981399536, 51.4554176331, 52.0126991272, 52.5815849304, 53.1504745483, 53.73097229, 54.3114738464, 54.8803634644, 55.4724693298, 56.06457901, 56.668296814, 57.2371864319, 57.8176841736, 58.3865737915, 58.9554634094, 59.5243530273, 60.0816307068, 60.6505203247, 61.2077980042, 61.7650794983, 62.3223571777, 62.8796348572, 63.4369163513, 64.0058059692, 64.5746917725, 65.1435852051, 65.7124710083, 66.2813568115, 66.8502502441, 67.4075241089, 67.964805603, 68.5220870972, 69.0793609619, 69.8456192017, 70.5886611938, 71.3316955566, 72.0863494873, 72.8409957886, 73.5840377808, 74.3270721436, 75.0817184448, 75.8363723755, 76.5794067383, 77.3224487305, 78.0770950317, 78.831741333, 79.5863952637, 80.3410415649, 81.0840835571, 81.8271179199, 82.5817642212, 83.3364181519, 84.0794525146, 84.8341064453, 85.5771408081, 86.3317871094, 87.0748291016, 87.8294754028, 88.5841217041, 89.3271636963, 90.0818099976, 90.8364639282, 91.579498291, 92.3225402832, 93.0771865845, 93.8318328857, 94.5748748779, 95.3179092407, 96.0725631714, 96.8272094727, 97.5818557739, 98.3365097046, 99.0795440674, 99.8225860596, 100.577232361, 101.331878662, 102.086524963, 102.841178894, 103.584213257, 104.327255249, 105.08190155, 105.836547852, 106.579589844, 107.322631836, 108.077278137, 108.831924438, 109.574966431, 110.329612732, 111.072654724, 111.827301025, 112.570335388, 113.336593628, 114.07963562, 114.834281921, 115.577323914, 116.331970215, 117.075012207, 117.81804657, 118.572692871, 119.327346802, 120.070381165, 120.825035095, 121.579681396, 122.322715759, 123.065757751, 123.820404053, 124.575057983, 125.318092346, 126.061134338, 126.804168701, 127.558815002, 128.313461304, 129.068115234, 129.822769165, 130.577407837, 131.332061768, 132.07510376, 132.818145752, 133.572784424, 134.327438354, 135.070480347, 135.825119019, 136.579772949, 137.322814941, 138.065841675, 138.820495605, 139.575149536, 140.329788208, 141.084442139, 141.850692749, 142.60534668, 143.185852051, 143.766342163, 144.346847534, 144.927337646, 145.507843018, 146.099945068, 146.680450439, 147.249343872, 147.818222046, 148.37550354, 148.944396973, 149.513290405, 150.070556641, 150.639450073, 151.208343506, 151.765625, 152.322906494, 152.880172729, 153.449066162, 154.017959595, 154.586837769, 155.155731201, 155.713012695, 156.270294189, 156.827575684, 157.384857178, 157.942123413, 158.511016846, 159.079910278, 159.637191772, 160.194458008, 160.751739502, 161.320632935, 161.889526367, 162.446792603, 163.004074097, 163.561355591, 164.130249023, 164.699142456, 165.256408691, 165.813690186, 166.382583618, 166.951477051, 167.508743286, 168.077636719, 168.634918213, 169.203811646, 169.761077881, 170.329971313, 170.898864746, 171.45614624, 172.013427734, 172.582305908, 173.151199341, 173.731704712, 174.312194824, 174.881088257, 175.473190308, 176.065307617, 176.669021606, 177.237915039, 177.818405151, 178.387298584, 178.956192017, 179.513473511, 180.070739746, 180.639633179, 181.208526611, 181.765808105, 182.323074341, 182.880355835, 183.437637329, 183.983306885, 184.505752563, 185.039810181, 185.573867798, 186.096328735, 186.641998291, 187.199264526, 187.768157959, 188.337051392, 189.080093384, 189.823120117, 190.577774048, 191.332427979, 192.075454712, 192.841720581, 193.584762573, 194.327789307, 195.082443237, 195.837097168, 196.58013916, 197.323165894, 198.077819824, 198.832473755, 199.587112427, 200.341766357, 201.08480835, 201.827835083, 202.582489014, 203.337142944, 204.080184937, 204.834823608, 205.577865601, 206.332519531, 207.075546265, 207.818588257, 208.573242188, 209.327880859, 210.08253479, 210.837188721, 211.580215454, 212.323257446, 213.077911377, 213.832565308, 214.575592041, 215.330245972, 216.084899902, 216.827926636, 217.582580566, 218.337234497, 219.08026123, 219.823303223, 220.577957153, 221.332611084, 222.087249756, 222.841903687, 223.584945679, 224.327972412, 225.082626343, 225.837280273, 226.580307007, 227.323348999, 228.07800293, 228.832641602, 229.575683594, 230.318725586, 231.073379517, 231.828018188, 232.571060181, 233.33732605, 234.080352783, 234.823394775, 235.578048706, 236.332687378, 237.07572937, 237.818771362, 238.573425293, 239.328063965, 240.071105957, 240.825759888, 241.58039856, 242.33505249, 243.078094482, 243.832733154, 244.575775146, 245.318817139, 246.061859131, 246.816497803, 247.559539795, 248.314193726, 249.068832397, 249.823486328, 250.578140259, 251.332778931, 252.075820923, 252.818862915, 253.573516846, 254.328155518, 255.07119751, 255.82585144, 256.568878174, 257.311920166, 258.066558838, 258.80960083, 259.56427002, 260.318908691, 261.073547363, 261.828216553, 262.571228027, 263.325897217, 264.068939209, 264.788757324, 265.496948242, 266.077453613, 266.657958984, 267.238464355, 267.818939209, 268.411071777, 269.003173828, 269.583679199, 270.164154053],
    "bpm_histogram": [0, 0, 0, 0, 0, 0, 0, 0, 0, 0, 0, 0, 0, 0, 0, 0, 0, 0, 0, 0, 0, 0, 0, 0, 0, 0, 0, 0, 0, 0, 0, 0, 0, 0, 0, 0, 0, 0, 0, 0, 0, 0, 0, 0, 0, 0, 0, 0, 0, 0, 0, 0, 0, 0, 0, 0, 0, 0, 0, 0, 0, 0, 0, 0, 0, 0, 0, 0, 0, 0, 0, 0, 0, 0, 0, 0, 0, 0.00249999994412, 0.0125000001863, 0, 0.330000013113, 0.232500001788, 0, 0.00249999994412, 0, 0.00249999994412, 0, 0, 0, 0, 0, 0, 0, 0, 0, 0, 0, 0, 0, 0.00499999988824, 0, 0.027499999851, 0, 0.0500000007451, 0, 0.165000006557, 0, 0, 0.155000001192, 0, 0.00499999988824, 0, 0.00499999988824, 0, 0, 0.00499999988824, 0, 0, 0, 0, 0, 0, 0, 0, 0, 0, 0, 0, 0, 0, 0, 0, 0, 0, 0, 0, 0, 0, 0, 0, 0, 0, 0, 0, 0, 0, 0, 0, 0, 0, 0, 0, 0, 0, 0, 0, 0, 0, 0, 0, 0, 0, 0, 0, 0, 0, 0, 0, 0, 0, 0, 0, 0, 0, 0, 0, 0, 0, 0, 0, 0, 0, 0, 0, 0, 0, 0, 0, 0, 0, 0, 0, 0, 0, 0, 0, 0, 0, 0, 0, 0, 0, 0, 0, 0, 0, 0, 0, 0, 0, 0, 0, 0, 0, 0, 0, 0, 0, 0, 0, 0, 0, 0, 0, 0, 0, 0, 0, 0, 0, 0, 0, 0, 0, 0, 0, 0, 0, 0, 0, 0, 0, 0, 0, 0, 0, 0, 0, 0, 0]
},
"tonal": {
    "chords_changes_rate": 0.0464279577136,
    "chords_number_rate": 0.0017132088542,
    "chords_strength": {
        "dmean": 0.00566669087857,
        "dmean2": 0.00579959200695,
        "dvar": 2.37145577557e-05,
        "dvar2": 3.0296134355e-05,
        "max": 0.766124844551,
        "mean": 0.462881833315,
        "median": 0.464681774378,
        "min": 0.270696133375,
        "stdev": 0.0820590481162,
        "var": 0.00673368712887
    },
    "hpcp_crest": {
        "dmean": 4.73908996582,
        "dmean2": 7.97174835205,
        "dvar": 26.344247818,
        "dvar2": 60.7583389282,
        "max": 35.8641738892,
        "mean": 15.2286062241,
        "median": 13.7826156616,
        "min": 0,
        "stdev": 7.28650140762,
        "var": 53.0931015015
    },
    "hpcp_entropy": {
        "dmean": 0.563912212849,
        "dmean2": 0.930287599564,
        "dvar": 0.285513997078,
        "dvar2": 0.708802461624,
        "max": 4.32462692261,
        "mean": 1.74321389198,
        "median": 1.72027051449,
        "min": 0,
        "stdev": 0.755243599415,
        "var": 0.570392906666
    },
    "key_edma": {
        "strength": 0.63441234827,
        "key": "A",
        "scale": "major"
    },
    "key_krumhansl": {
        "strength": 0.620987892151,
        "key": "A",
        "scale": "major"
    },
    "key_temperley": {
        "strength": 0.602785050869,
        "key": "A",
        "scale": "major"
    },
    "tuning_diatonic_strength": 0.596497058868,
    "tuning_equal_tempered_deviation": 0.299346923828,
    "tuning_frequency": 434.193115234,
    "tuning_nontempered_energy_ratio": 0.994425237179,
    "hpcp": {
        "dmean": [0.072771050036, 0.0772001445293, 0.0779982507229, 0.0662211105227, 0.0386867523193, 0.0308243148029, 0.0386631451547, 0.0492018088698, 0.0458813160658, 0.0385532453656, 0.0398588851094, 0.0430312044919, 0.0349457524717, 0.0345587581396, 0.0291045084596, 0.0342050008476, 0.0384982228279, 0.0303350035101, 0.0260536037385, 0.0262811798602, 0.0287876240909, 0.132504627109, 0.148428484797, 0.179647907615, 0.0883752554655, 0.0540959015489, 0.0450317151845, 0.0474041067064, 0.0490291044116, 0.0513267330825, 0.0968556255102, 0.0845335423946, 0.103525087237, 0.103799894452, 0.0936179310083, 0.0978010222316],
        "dmean2": [0.134347274899, 0.136170074344, 0.140711098909, 0.1195737198, 0.0745885670185, 0.0587676465511, 0.0692951604724, 0.0809964165092, 0.0806750580668, 0.0733609125018, 0.0755396783352, 0.081682741642, 0.0654438734055, 0.0633550286293, 0.0538040660322, 0.0561105720699, 0.0642218589783, 0.0555934496224, 0.0482270792127, 0.0482329465449, 0.0534967966378, 0.223906472325, 0.266774982214, 0.311157166958, 0.166518837214, 0.10279622674, 0.0857088491321, 0.0873064473271, 0.0870504677296, 0.0965837985277, 0.173946350813, 0.15805952251, 0.190065652132, 0.189512521029, 0.169139176607, 0.180633231997],
        "dvar": [0.0321067757905, 0.0269075985998, 0.0284511800855, 0.0247431565076, 0.0152413826436, 0.011058983393, 0.0111092990264, 0.0152559680864, 0.0162578783929, 0.0178517829627, 0.0201998669654, 0.0215198844671, 0.0182098560035, 0.0152812013403, 0.0125069422647, 0.00869042705745, 0.0134673025459, 0.0118830529973, 0.0101600056514, 0.00987826194614, 0.00940130092204, 0.0296653285623, 0.0818181633949, 0.0572378337383, 0.0409253463149, 0.0307499244809, 0.0239945631474, 0.0218798667192, 0.0207625832409, 0.0257392860949, 0.0477956570685, 0.0558689720929, 0.0439770258963, 0.0368179492652, 0.0437754616141, 0.0382228605449],
        "dvar2": [0.0885567292571, 0.0725096687675, 0.0781397745013, 0.0703521892428, 0.0442423857749, 0.0320166572928, 0.0312713347375, 0.039686512202, 0.0459030382335, 0.0519260056317, 0.0580298379064, 0.0626693069935, 0.0472574643791, 0.0388981513679, 0.0344651266932, 0.0236897394061, 0.0344838052988, 0.0326335839927, 0.0298524275422, 0.0276782866567, 0.0270481873304, 0.0768519043922, 0.1893145293, 0.165752723813, 0.112445019186, 0.0847102627158, 0.0693734139204, 0.0629651471972, 0.060007084161, 0.0755184069276, 0.135136708617, 0.144295543432, 0.130820065737, 0.103450350463, 0.115279324353, 0.10815102607],
        "max": [1, 1, 1, 1, 1, 1, 1, 1, 1, 1, 1, 1, 1, 1, 1, 1, 1, 1, 1, 1, 1, 1, 1, 1, 1, 1, 1, 1, 1, 1, 1, 1, 1, 1, 1, 1],
        "mean": [0.0647228732705, 0.13914526999, 0.171580150723, 0.0865784808993, 0.0228770337999, 0.0189784578979, 0.0524944365025, 0.105615049601, 0.0725932046771, 0.0259865261614, 0.0310369264334, 0.0321378558874, 0.0672780200839, 0.0639744102955, 0.0216380767524, 0.0425546988845, 0.0565431416035, 0.0312878936529, 0.0202686749399, 0.0233293157071, 0.0213461127132, 0.192106679082, 0.486595988274, 0.339007973671, 0.0606570653617, 0.0439743511379, 0.0306667685509, 0.0406981147826, 0.0487962067127, 0.0364769399166, 0.104015953839, 0.158681109548, 0.0918658748269, 0.170915529132, 0.240423887968, 0.113952092826],
        "median": [0.00815976317972, 0.020781300962, 0.0129776429385, 0.00638062739745, 0.000848939293064, 0.000654266681522, 0.00378156639636, 0.00589481182396, 0.00340070645325, 0.00103325746022, 0.000952931935899, 0.000817624852061, 0.00191058765631, 0.00225220620632, 0.00166506529786, 0.00383219262585, 0.0040940111503, 0.00213765283115, 0.000929814530537, 0.000836752646137, 0.00146232789848, 0.0837139934301, 0.33934032917, 0.261299073696, 0.00151834904682, 0.000847505580168, 0.000865599722601, 0.00365359522402, 0.00441745296121, 0.00232356297784, 0.00233362149447, 0.00316945603117, 0.00305316806771, 0.00616996921599, 0.00650772126392, 0.00378299783915],
        "min": [0, 0, 0, 0, 0, 0, 0, 0, 0, 0, 0, 0, 0, 0, 0, 0, 0, 0, 0, 0, 0, 0, 0, 0, 0, 0, 0, 0, 0, 0, 0, 0, 0, 0, 0, 0],
        "stdev": [0.168350175023, 0.236514523625, 0.302082598209, 0.171735331416, 0.0927815511823, 0.0807572603226, 0.108619935811, 0.197035312653, 0.142943114042, 0.102293878794, 0.12173858285, 0.119927980006, 0.226606056094, 0.211331754923, 0.0983765274286, 0.0969562977552, 0.142331033945, 0.113879308105, 0.086955986917, 0.102658189833, 0.0864913016558, 0.211229816079, 0.462603271008, 0.34088331461, 0.171908378601, 0.171329036355, 0.125246271491, 0.120265513659, 0.127122506499, 0.128076553345, 0.238743677735, 0.343189477921, 0.204806938767, 0.2464453578, 0.348282694817, 0.222745537758],
        "var": [0.0283417832106, 0.0559391230345, 0.0912538915873, 0.0294930245727, 0.00860841572285, 0.0065217348747, 0.0117982905358, 0.0388229116797, 0.020432734862, 0.0104640377685, 0.0148202823475, 0.0143827199936, 0.0513503029943, 0.0446611084044, 0.0096779409796, 0.00940052419901, 0.0202581249177, 0.0129684964195, 0.00756134418771, 0.010538703762, 0.00748074473813, 0.0446180328727, 0.214001789689, 0.116201430559, 0.0295524913818, 0.0293536409736, 0.0156866293401, 0.0144637934864, 0.0161601323634, 0.0164036042988, 0.0569985434413, 0.117779009044, 0.0419458821416, 0.0607353150845, 0.121300831437, 0.049615573138]
    },
    "chords_histogram": [34.2299118042, 4.72845649719, 10.3820457458, 0, 0, 0, 0, 0, 0, 0, 0, 0.051396265626, 0.0685283541679, 0.17132088542, 0, 2.00445437431, 0.0856604427099, 20.7298278809, 8.25766658783, 5.10536241531, 0, 7.62377929688, 3.82045578957, 2.74113416672],
    "thpcp": [1, 0.696692883968, 0.124655909836, 0.0903713777661, 0.0630230605602, 0.08363840729, 0.100280739367, 0.0749635025859, 0.213762462139, 0.326104432344, 0.188792914152, 0.351247310638, 0.494093447924, 0.234182149172, 0.133011519909, 0.285956472158, 0.352613151073, 0.177926823497, 0.0470144301653, 0.0390024967492, 0.107880949974, 0.217048749328, 0.149185791612, 0.053404726088, 0.0637837722898, 0.066046282649, 0.138262584805, 0.131473362446, 0.0444682613015, 0.0874538645148, 0.116201415658, 0.064299531281, 0.0416540130973, 0.0479439124465, 0.0438682474196, 0.394797086716],
    "chords_key": "A",
    "chords_scale": "major"
}
}